Workbook

Sheet Summary
C2: Man Group | AUM to earnings
C4: Case selected | D4: =Assumptions!$E$4 -> Base
C5: 2023–2025 history | H1 2026 actual | Q3 2026–2027 forecast | 14 Sep 2026
D7: H1:23 | E7: FY:23 | F7: H1:24 | G7: FY:24 | H7: H1:25 | I7: FY:25 | J7: H1:26 | K7: FY:26 | L7: H1:27 | M7: FY:27
D8: Actual | E8: Actual | F8: Actual | G8: Actual | H8: Actual | I8: Actual | J8: Actual | K8: A + F | L8: Forecast | M8: Forecast
C9: Closing AUM, USD bn | D9: ='Fee engine'!D87 -> 151.7 | E9: ='Fee engine'!E87 -> 167.5 | F9: ='Fee engine'!F87 -> 178.2 | G9: ='Fee engine'!G87 -> 168.6 | H9: ='Fee engine'!H87 -> 193.3 | I9: ='Fee engine'!I87 -> 227.6 | J9: ='Fee engine'!J87 -> 253.6 | K9: ='Fee engine'!K87 -> 266.4385 | ... M9: ='Fee engine'!M87 -> 294.09825
C10: Net flows, USD bn | D10: ='Fee engine'!D89 -> 2.6 | E10: ='Fee engine'!E89 -> 3 | F10: ='Fee engine'!F89 -> 0.9 | G10: ='Fee engine'!G89 -> -3.3 | H10: ='Fee engine'!H89 -> 17.6 | I10: ='Fee engine'!I89 -> 28.7 | J10: ='Fee engine'!J89 -> 7.1 | K10: ='Fee engine'!K89 -> 12.2354 | ... M10: ='Fee engine'!M89 -> 11.0639
C11: Implied net fee margin, annual bp | D11: ='Fee engine'!D109 -> 62.970568 | E11: ='Fee engine'!E109 -> 62.838499 | F11: ='Fee engine'!F109 -> 63.233395 | G11: ='Fee engine'!G109 -> 62.969075 | H11: ='Fee engine'!H109 -> 58.492434 | I11: ='Fee engine'!I109 -> 55.379869 | J11: ='Fee engine'!J109 -> 53.441296 | K11: ='Fee engine'!K109 -> 54.786162 | ... M11: ='Fee engine'!M109 -> 56
C13: Net management fees, USD m | D13: ='Fee engine'!D95 -> 460 | E13: ='Fee engine'!E95 -> 963 | F13: ='Fee engine'!F95 -> 551 | G13: ='Fee engine'!G95 -> 1097 | H13: ='Fee engine'!H95 -> 517 | I13: ='Fee engine'!I95 -> 1077 | J13: ='Fee engine'!J95 -> 627 | K13: ='Fee engine'!K95 -> 1354.9429 | ... M13: ='Fee engine'!M95 -> 1568.3079
C14: Performance fees, USD m | D14: ='Fee engine'!D96 -> 32 | E14: ='Fee engine'!E96 -> 180 | F14: ='Fee engine'!F96 -> 170 | G14: ='Fee engine'!G96 -> 310 | H14: ='Fee engine'!H96 -> 67 | I14: ='Fee engine'!I96 -> 281 | J14: ='Fee engine'!J96 -> 207 | K14: ='Fee engine'!K96 -> 421 | ... M14: ='Fee engine'!M96 -> 281
C15: Seed gains, USD m | D15: ='Fee engine'!D97 -> 19 | E15: ='Fee engine'!E97 -> 48 | F15: ='Fee engine'!F97 -> 39 | G15: ='Fee engine'!G97 -> 50 | H15: ='Fee engine'!H97 -> 19 | I15: ='Fee engine'!I97 -> 38 | J15: ='Fee engine'!J97 -> 18 | K15: ='Fee engine'!K97 -> 37 | ... M15: ='Fee engine'!M97 -> 38
C16: Rental / other income, USD m | D16: ='Fee engine'!D98 -> 2 | E16: ='Fee engine'!E98 -> 5 | F16: ='Fee engine'!F98 -> 1 | G16: ='Fee engine'!G98 -> 2 | H16: ='Fee engine'!H98 -> 1 | I16: ='Fee engine'!I98 -> 2 | J16: ='Fee engine'!J98 -> 1 | K16: ='Fee engine'!K98 -> 2 | ... M16: ='Fee engine'!M98 -> 2
C17: Core net revenue, USD m | D17: ='Fee engine'!D99 -> 513 | E17: ='Fee engine'!E99 -> 1196 | F17: ='Fee engine'!F99 -> 761 | G17: ='Fee engine'!G99 -> 1459 | H17: ='Fee engine'!H99 -> 604 | I17: ='Fee engine'!I99 -> 1398 | J17: ='Fee engine'!J99 -> 853 | K17: ='Fee engine'!K99 -> 1814.9429 | ... M17: ='Fee engine'!M99 -> 1889.3079
C19: Core operating costs, USD m | D19: ='Fee engine'!D100 -> -370 | E19: ='Fee engine'!E100 -> -834 | F19: ='Fee engine'!F100 -> -487 | G19: ='Fee engine'!G100 -> -960 | H19: ='Fee engine'!H100 -> -449 | I19: ='Fee engine'!I100 -> -970 | J19: ='Fee engine'!J100 -> -546 | K19: ='Fee engine'!K100 -> -1124.4043 | ... M19: ='Fee engine'!M100 -> -1096.5538
C20: Core operating profit, USD m | D20: ='Fee engine'!D101 -> 143 | E20: ='Fee engine'!E101 -> 362 | F20: ='Fee engine'!F101 -> 274 | G20: ='Fee engine'!G101 -> 499 | H20: ='Fee engine'!H101 -> 155 | I20: ='Fee engine'!I101 -> 428 | J20: ='Fee engine'!J101 -> 307 | K20: ='Fee engine'!K101 -> 690.53863 | ... M20: ='Fee engine'!M101 -> 792.75411
C22: Management-fee PBT, USD m | D22: ='Fee engine'!D102 -> 133 | E22: ='Fee engine'!E102 -> 280 | F22: ='Fee engine'!F102 -> 163 | G22: ='Fee engine'!G102 -> 323 | H22: ='Fee engine'!H102 -> 130 | I22: ='Fee engine'!I102 -> 294 | J22: ='Fee engine'!J102 -> 186 | K22: ='Fee engine'!K102 -> 473.73769 | ... M22: ='Fee engine'!M102 -> 658.75411
C23: Performance / seed PBT, USD m | D23: ='Fee engine'!D103 -> 4 | E23: ='Fee engine'!E103 -> 60 | F23: ='Fee engine'!F103 -> 94 | G23: ='Fee engine'!G103 -> 150 | H23: ='Fee engine'!H103 -> 16 | I23: ='Fee engine'!I103 -> 113 | J23: ='Fee engine'!J103 -> 111 | K23: ='Fee engine'!K103 -> 196.03937 | ... M23: ='Fee engine'!M103 -> 113
C24: Core total PBT, USD m | D24: ='Fee engine'!D104 -> 137 | E24: ='Fee engine'!E104 -> 340 | F24: ='Fee engine'!F104 -> 257 | G24: ='Fee engine'!G104 -> 473 | H24: ='Fee engine'!H104 -> 146 | I24: ='Fee engine'!I104 -> 407 | J24: ='Fee engine'!J104 -> 297 | K24: ='Fee engine'!K104 -> 669.77706 | ... M24: ='Fee engine'!M104 -> 771.75411
C25: Core tax expense, USD m | D25: ='Fee engine'!D105 -> -29 | E25: ='Fee engine'!E105 -> -69 | F25: ='Fee engine'!F105 -> -53 | G25: ='Fee engine'!G105 -> -92 | H25: ='Fee engine'!H105 -> -33 | I25: ='Fee engine'!I105 -> -86 | J25: ='Fee engine'!J105 -> -67 | K25: ='Fee engine'!K105 -> -145.76862 | ... M25: ='Fee engine'!M105 -> -163.07335
C26: Core profit after tax, USD m | D26: ='Fee engine'!D106 -> 108 | E26: ='Fee engine'!E106 -> 271 | F26: ='Fee engine'!F106 -> 204 | G26: ='Fee engine'!G106 -> 381 | H26: ='Fee engine'!H106 -> 113 | I26: ='Fee engine'!I106 -> 321 | J26: ='Fee engine'!J106 -> 230 | K26: ='Fee engine'!K106 -> 524.00844 | ... M26: ='Fee engine'!M106 -> 608.68076
C27: Diluted weighted shares, m | D27: ='Fee engine'!D107 -> 1217 | E27: ='Fee engine'!E107 -> 1207.0554 | F27: ='Fee engine'!F107 -> 1192 | G27: ='Fee engine'!G107 -> 1189.0758 | H27: ='Fee engine'!H107 -> 1168 | I27: ='Fee engine'!I107 -> 1164.8774 | J27: ='Fee engine'!J107 -> 1153 | K27: ='Fee engine'!K107 -> 1158.9875 | ... M27: ='Fee engine'!M107 -> 1164.8774
C28: Core diluted EPS, US cents | D28: ='Fee engine'!D108 -> 8.874281 | E28: ='Fee engine'!E108 -> 22.45133 | F28: ='Fee engine'!F108 -> 17.114094 | G28: ='Fee engine'!G108 -> 32.04169 | H28: ='Fee engine'!H108 -> 9.6746575 | I28: ='Fee engine'!I108 -> 27.556549 | J28: ='Fee engine'!J108 -> 19.947962 | K28: ='Fee engine'!K108 -> 45.212606 | ... M28: ='Fee engine'!M108 -> 52.252776
C31: THESIS QUESTIONS | USE THE CASE SELECTOR
C33: Fee margin | D33: Base holds the 2025 average of 56bp; Downside uses 52bp, matching H1 2026.
C34: Flows | D34: Base +1% of opening AUM per quarter; Downside 0%; Upside +2%.
C35: Performance fees | D35: Base repeats allocated 2025 quarters; Zero PF removes forecast fees and their variable costs.
C36: Zero PF interpretation | D36: H1 2026 remains actual. FY2027 is the full-year zero-fee test; seed gains and funding stay.
C37: Quarterly evidence | D37: AUM is reported; quarterly financial flows are estimates tied to disclosed H1 and FY totals.
C40: 2025 MIX | THE SAME AUM DOES NOT EARN THE SAME FEES
C41: Product category | D41: AUM share | E41: Fee share | F41: Fee margin, bp
C42: Absolute return | D42: =Disclosures!D61/'Fee engine'!O17 -> 0.18673111 | E42: =Disclosures!E61/Disclosures!I22 -> 0.39554318 | F42: =Disclosures!F61 -> 105
C43: Total return | D43: =Disclosures!D62/'Fee engine'!O17 -> 0.20474517 | E43: =Disclosures!E62/Disclosures!I22 -> 0.24976787 | F43: =Disclosures!F62 -> 63
C44: Multi-manager | D44: =Disclosures!D63/'Fee engine'!O17 -> 0.06370826 | E44: =Disclosures!E63/Disclosures!I22 -> 0.025998143 | F44: =Disclosures!F63 -> 20
C45: Systematic long-only | D45: =Disclosures!D64/'Fee engine'!O17 -> 0.33479789 | E45: =Disclosures!E64/Disclosures!I22 -> 0.12627669 | F45: =Disclosures!F64 -> 24
C46: Discretionary long-only | D46: =Disclosures!D65/'Fee engine'!O17 -> 0.21001757 | E46: =Disclosures!E65/Disclosures!I22 -> 0.1996286 | F46: =Disclosures!F65 -> 57
C48: Performance fees reflect hurdles, high-water marks and crystallisation; AUM returns do not mechanically imply fees.
C52: Year | D52: Mgmt PBT | E52: PF / seed PBT | F52: Total PBT
C53: FY:23 | D53: ='Fee engine'!E102 -> 280 | E53: ='Fee engine'!E103 -> 60 | F53: ='Fee engine'!E104 -> 340
C54: FY:24 | D54: ='Fee engine'!G102 -> 323 | E54: ='Fee engine'!G103 -> 150 | F54: ='Fee engine'!G104 -> 473
C55: FY:25 | D55: ='Fee engine'!I102 -> 294 | E55: ='Fee engine'!I103 -> 113 | F55: ='Fee engine'!I104 -> 407
C56: FY:26 | D56: ='Fee engine'!K102 -> 473.73769 | E56: ='Fee engine'!K103 -> 196.03937 | F56: ='Fee engine'!K104 -> 669.77706
C57: FY:27 | D57: ='Fee engine'!M102 -> 658.75411 | E57: ='Fee engine'!M103 -> 113 | F57: ='Fee engine'!M104 -> 771.75411

Sheet Assumptions
C2: Man Group | scenario controls
C4: Case number (1–4) | D4: 1 | E4: =CHOOSE(D4,"Base","Downside","Upside","Zero PF") -> Base
C5: 1 Base | 2 Downside | 3 Upside | 4 Zero PF. Cases affect Q3 2026 onward only.
D7: Q1:23 | E7: Q2:23 | F7: Q3:23 | G7: Q4:23 | H7: Q1:24 | I7: Q2:24 | J7: Q3:24 | K7: Q4:24 | L7: Q1:25 | M7: Q2:25 | N7: Q3:25 | O7: Q4:25 | P7: Q1:26 | Q7: Q2:26 | R7: Q3:26 | S7: Q4:26 | T7: Q1:27 | U7: Q2:27 | V7: Q3:27 | W7: Q4:27
C10: Net flows / opening AUM
C11: Active selection | D11: ='Fee engine'!D19 -> 0.0076762038 | E11: ='Fee engine'!E19 -> 0.010366275 | F11: ='Fee engine'!F19 -> 0.0046143705 | G11: ='Fee engine'!G19 -> -0.0018610422 | H11: ='Fee engine'!H19 -> -0.0095522388 | I11: ='Fee engine'!I19 -> 0.014228799 | J11: ='Fee engine'!J19 -> -0.030864198 | K11: ='Fee engine'!K19 -> 0.0074328188 | ... Q11: ='Fee engine'!Q19 -> 0.038041102 | R11: =IF(CHOOSE($D$4,ISBLANK(R12),ISBLANK(R13),ISBLANK(R14),ISBLANK(R15)),NA(),CHOOSE($D$4,R12,R13,R14,R15)) -> 0.01 | S11: =IF(CHOOSE($D$4,ISBLANK(S12),ISBLANK(S13),ISBLANK(S14),ISBLANK(S15)),NA(),CHOOSE($D$4,S12,S13,S14,S15)) -> 0.01 | T11: =IF(CHOOSE($D$4,ISBLANK(T12),ISBLANK(T13),ISBLANK(T14),ISBLANK(T15)),NA(),CHOOSE($D$4,T12,T13,T14,T15)) -> 0.01 | U11: =IF(CHOOSE($D$4,ISBLANK(U12),ISBLANK(U13),ISBLANK(U14),ISBLANK(U15)),NA(),CHOOSE($D$4,U12,U13,U14,U15)) -> 0.01 | V11: =IF(CHOOSE($D$4,ISBLANK(V12),ISBLANK(V13),ISBLANK(V14),ISBLANK(V15)),NA(),CHOOSE($D$4,V12,V13,V14,V15)) -> 0.01 | W11: =IF(CHOOSE($D$4,ISBLANK(W12),ISBLANK(W13),ISBLANK(W14),ISBLANK(W15)),NA(),CHOOSE($D$4,W12,W13,W14,W15)) -> 0.01
C12: Base | R12: 0.01 | S12: 0.01 | T12: 0.01 | U12: 0.01 | V12: 0.01 | W12: 0.01
C13: Downside | R13: 0 | S13: 0 | T13: 0 | U13: 0 | V13: 0 | W13: 0
C14: Upside | R14: 0.02 | S14: 0.02 | T14: 0.02 | U14: 0.02 | V14: 0.02 | W14: 0.02
C15: Zero PF | R15: 0.01 | S15: 0.01 | T15: 0.01 | U15: 0.01 | V15: 0.01 | W15: 0.01
C17: Investment return / opening AUM
C18: Active selection | D18: ='Fee engine'!D20 -> 0.0048848569 | E18: ='Fee engine'!E20 -> 0.03040774 | F18: ='Fee engine'!F20 -> 0.00065919578 | G18: ='Fee engine'!G20 -> 0.027915633 | H18: ='Fee engine'!H20 -> 0.058507463 | I18: ='Fee engine'!I20 -> 0.0073989755 | J18: ='Fee engine'!J20 -> 0.0022446689 | K18: ='Fee engine'!K20 -> -0.0034305317 | ... Q18: ='Fee engine'!Q20 -> 0.073021425 | R18: =IF(CHOOSE($D$4,ISBLANK(R19),ISBLANK(R20),ISBLANK(R21),ISBLANK(R22)),NA(),CHOOSE($D$4,R19,R20,R21,R22)) -> 0.015 | S18: =IF(CHOOSE($D$4,ISBLANK(S19),ISBLANK(S20),ISBLANK(S21),ISBLANK(S22)),NA(),CHOOSE($D$4,S19,S20,S21,S22)) -> 0.015 | T18: =IF(CHOOSE($D$4,ISBLANK(T19),ISBLANK(T20),ISBLANK(T21),ISBLANK(T22)),NA(),CHOOSE($D$4,T19,T20,T21,T22)) -> 0.015 | U18: =IF(CHOOSE($D$4,ISBLANK(U19),ISBLANK(U20),ISBLANK(U21),ISBLANK(U22)),NA(),CHOOSE($D$4,U19,U20,U21,U22)) -> 0.015 | V18: =IF(CHOOSE($D$4,ISBLANK(V19),ISBLANK(V20),ISBLANK(V21),ISBLANK(V22)),NA(),CHOOSE($D$4,V19,V20,V21,V22)) -> 0.015 | W18: =IF(CHOOSE($D$4,ISBLANK(W19),ISBLANK(W20),ISBLANK(W21),ISBLANK(W22)),NA(),CHOOSE($D$4,W19,W20,W21,W22)) -> 0.015
C19: Base | R19: 0.015 | S19: 0.015 | T19: 0.015 | U19: 0.015 | V19: 0.015 | W19: 0.015
C20: Downside | R20: 0.015 | S20: 0.015 | T20: 0.015 | U20: 0.015 | V20: 0.015 | W20: 0.015
C21: Upside | R21: 0.015 | S21: 0.015 | T21: 0.015 | U21: 0.015 | V21: 0.015 | W21: 0.015
C22: Zero PF | R22: 0.015 | S22: 0.015 | T22: 0.015 | U22: 0.015 | V22: 0.015 | W22: 0.015
C24: Net management-fee margin
C25: Active selection | D25: ='Fee engine'!D26 -> 62.970568 | E25: ='Fee engine'!E26 -> 62.970568 | F25: ='Fee engine'!F26 -> 62.718204 | G25: ='Fee engine'!G26 -> 62.718204 | H25: ='Fee engine'!H26 -> 63.233395 | I25: ='Fee engine'!I26 -> 63.233395 | J25: ='Fee engine'!J26 -> 62.704565 | K25: ='Fee engine'!K26 -> 62.704565 | ... Q25: ='Fee engine'!Q26 -> 53.441296 | R25: =IF(CHOOSE($D$4,ISBLANK(R26),ISBLANK(R27),ISBLANK(R28),ISBLANK(R29)),NA(),CHOOSE($D$4,R26,R27,R28,R29)) -> 56 | S25: =IF(CHOOSE($D$4,ISBLANK(S26),ISBLANK(S27),ISBLANK(S28),ISBLANK(S29)),NA(),CHOOSE($D$4,S26,S27,S28,S29)) -> 56 | T25: =IF(CHOOSE($D$4,ISBLANK(T26),ISBLANK(T27),ISBLANK(T28),ISBLANK(T29)),NA(),CHOOSE($D$4,T26,T27,T28,T29)) -> 56 | U25: =IF(CHOOSE($D$4,ISBLANK(U26),ISBLANK(U27),ISBLANK(U28),ISBLANK(U29)),NA(),CHOOSE($D$4,U26,U27,U28,U29)) -> 56 | V25: =IF(CHOOSE($D$4,ISBLANK(V26),ISBLANK(V27),ISBLANK(V28),ISBLANK(V29)),NA(),CHOOSE($D$4,V26,V27,V28,V29)) -> 56 | W25: =IF(CHOOSE($D$4,ISBLANK(W26),ISBLANK(W27),ISBLANK(W28),ISBLANK(W29)),NA(),CHOOSE($D$4,W26,W27,W28,W29)) -> 56
C26: Base | R26: =$D$50 -> 56 | S26: =$D$50 -> 56 | T26: =$D$50 -> 56 | U26: =$D$50 -> 56 | V26: =$D$50 -> 56 | W26: =$D$50 -> 56
C27: Downside | R27: 52 | S27: 52 | T27: 52 | U27: 52 | V27: 52 | W27: 52
C28: Upside | R28: 58 | S28: 58 | T28: 58 | U28: 58 | V28: 58 | W28: 58
C29: Zero PF | R29: =$D$50 -> 56 | S29: =$D$50 -> 56 | T29: =$D$50 -> 56 | U29: =$D$50 -> 56 | V29: =$D$50 -> 56 | W29: =$D$50 -> 56
C31: Performance-fee revenue, USD m
C32: Active selection | D32: ='Fee engine'!D28 -> 3.2 | E32: ='Fee engine'!E28 -> 28.8 | F32: ='Fee engine'!F28 -> 14.8 | G32: ='Fee engine'!G28 -> 133.2 | H32: ='Fee engine'!H28 -> 17 | I32: ='Fee engine'!I28 -> 153 | J32: ='Fee engine'!J28 -> 14 | K32: ='Fee engine'!K28 -> 126 | ... Q32: ='Fee engine'!Q28 -> 186.3 | R32: =IF(CHOOSE($D$4,ISBLANK(R33),ISBLANK(R34),ISBLANK(R35),ISBLANK(R36)),NA(),CHOOSE($D$4,R33,R34,R35,R36)) -> 21.4 | S32: =IF(CHOOSE($D$4,ISBLANK(S33),ISBLANK(S34),ISBLANK(S35),ISBLANK(S36)),NA(),CHOOSE($D$4,S33,S34,S35,S36)) -> 192.6 | T32: =IF(CHOOSE($D$4,ISBLANK(T33),ISBLANK(T34),ISBLANK(T35),ISBLANK(T36)),NA(),CHOOSE($D$4,T33,T34,T35,T36)) -> 6.7 | U32: =IF(CHOOSE($D$4,ISBLANK(U33),ISBLANK(U34),ISBLANK(U35),ISBLANK(U36)),NA(),CHOOSE($D$4,U33,U34,U35,U36)) -> 60.3 | V32: =IF(CHOOSE($D$4,ISBLANK(V33),ISBLANK(V34),ISBLANK(V35),ISBLANK(V36)),NA(),CHOOSE($D$4,V33,V34,V35,V36)) -> 21.4 | W32: =IF(CHOOSE($D$4,ISBLANK(W33),ISBLANK(W34),ISBLANK(W35),ISBLANK(W36)),NA(),CHOOSE($D$4,W33,W34,W35,W36)) -> 192.6
C33: Base | R33: ='Fee engine'!N28*$D$44 -> 21.4 | S33: ='Fee engine'!O28*$D$44 -> 192.6 | T33: ='Fee engine'!L28*$D$44 -> 6.7 | U33: ='Fee engine'!M28*$D$44 -> 60.3 | V33: ='Fee engine'!N28*$D$44 -> 21.4 | W33: ='Fee engine'!O28*$D$44 -> 192.6
C34: Downside | R34: ='Fee engine'!N28*$D$45 -> 10.7 | S34: ='Fee engine'!O28*$D$45 -> 96.3 | T34: ='Fee engine'!L28*$D$45 -> 3.35 | U34: ='Fee engine'!M28*$D$45 -> 30.15 | V34: ='Fee engine'!N28*$D$45 -> 10.7 | W34: ='Fee engine'!O28*$D$45 -> 96.3
C35: Upside | R35: ='Fee engine'!N28*$D$46 -> 32.1 | S35: ='Fee engine'!O28*$D$46 -> 288.9 | T35: ='Fee engine'!L28*$D$46 -> 10.05 | U35: ='Fee engine'!M28*$D$46 -> 90.45 | V35: ='Fee engine'!N28*$D$46 -> 32.1 | W35: ='Fee engine'!O28*$D$46 -> 288.9
C36: Zero PF | R36: 0 | S36: 0 | T36: 0 | U36: 0 | V36: 0 | W36: 0
C40: QUARTERLY ALLOCATION AND BASE-YEAR CALIBRATION
C41: Q1 share of H1 performance fees | D41: 0.1
C42: Q3 share of H2 performance fees | D42: 0.1
C43: Equal-quarter allocation factor | D43: 0.5
C44: Base performance-fee multiplier | D44: 1
C45: Downside performance-fee multiplier | D45: 0.5
C46: Upside performance-fee multiplier | D46: 1.5
C48: Quarter fraction of year | D48: 0.25
C49: USD millions per USD billion | D49: 1000
C50: FY2025 published average fee margin | D50: =Disclosures!I45 -> 56
C51: FY2025 management variable compensation ratio | D51: =(Disclosures!I28-Disclosures!I27)/Disclosures!I22 -> 0.19220056
C52: FY2025 PF / seed variable compensation ratio | D52: =Disclosures!I29/SUM(Disclosures!I23,Disclosures!I24) -> 0.60815047
C53: FY2025 servicing / average AUM, annual bp | D53: =Disclosures!I26/AVERAGE('Fee engine'!L18:O18)/$D$49*$D$60 -> 3.7536958
C54: Fixed compensation, quarterly USD m | D54: =Disclosures!I27*$D$48 -> 68.5
C55: Other fixed costs incl D&A, quarterly USD m | D55: =Disclosures!I30*$D$48 -> 53.75
C56: Core tax rate: FY2025 actual expense / PBT | D56: =Disclosures!I39/Disclosures!I38 -> 0.21130221
C57: Diluted shares, FY2025 weighted average m | D57: =Disclosures!I41 -> 1164.8774
C58: Seed gains, quarterly USD m | D58: =Disclosures!I24*$D$48 -> 9.5
C59: Rental / other income, quarterly USD m | D59: =Disclosures!I25*$D$48 -> 0.5
C60: Basis points per unit rate | D60: 10000
C61: US cents per US dollar | D61: 100
C62: Other employment, quarterly USD m | D62: =Disclosures!I31*$D$48 -> 1.75
C63: Management finance expense, quarterly USD m | D63: =Disclosures!I32*$D$48 -> 1.75
C64: PF / seed finance expense, quarterly USD m | D64: =Disclosures!I33*$D$48 -> 2.75
C65: Management third-party share, quarterly USD m | D65: =Disclosures!I34*$D$48 -> 0.5
C66: PF third-party profit share / fee revenue | D66: =Disclosures!I35/Disclosures!I23 -> 0.0035587189
C67: Forecast FX / acquisitions / other, USD bn | D67: 0

Sheet Fee engine
C2: Man Group | quarterly fee engine
C4: Case selected | D4: =Assumptions!$E$4 -> Base
C5: USD bn AUM | USD m income and costs | EPS US cents | core basis
D6: 45016 | E6: 45107 | F6: 45199 | G6: 45291 | H6: 45382 | I6: 45473 | J6: 45565 | K6: 45657 | L6: 45747 | M6: 45838 | N6: 45930 | O6: 46022 | P6: 46112 | Q6: 46203 | R6: 46295 | S6: 46387 | T6: 46477 | U6: 46568 | V6: 46660 | W6: 46752
D7: Q1:23 | E7: Q2:23 | F7: Q3:23 | G7: Q4:23 | H7: Q1:24 | I7: Q2:24 | J7: Q3:24 | K7: Q4:24 | L7: Q1:25 | M7: Q2:25 | N7: Q3:25 | O7: Q4:25 | P7: Q1:26 | Q7: Q2:26 | R7: Q3:26 | S7: Q4:26 | T7: Q1:27 | U7: Q2:27 | V7: Q3:27 | W7: Q4:27
D8: AUM A / P&L E | E8: AUM A / P&L E | F8: AUM A / P&L E | G8: AUM A / P&L E | H8: AUM A / P&L E | I8: AUM A / P&L E | J8: AUM A / P&L E | K8: AUM A / P&L E | L8: AUM A / P&L E | M8: AUM A / P&L E | N8: AUM A / P&L E | O8: AUM A / P&L E | P8: AUM A / P&L E | Q8: AUM A / P&L E | R8: Forecast | S8: Forecast | T8: Forecast | U8: Forecast | V8: Forecast | W8: Forecast
C9: AUM | STOCK TO PERIOD REVENUE
C10: Opening fee-paying AUM | D10: =Disclosures!D9 -> 143.3 | E10: =D17 -> 144.7 | F10: =E17 -> 151.7 | G10: =F17 -> 161.2 | H10: =G17 -> 167.5 | I10: =H17 -> 175.7 | J10: =I17 -> 178.2 | K10: =J17 -> 174.9 | L10: =K17 -> 168.6 | ... W10: =V17 -> 286.92512
C11: Net flows | D11: =Disclosures!D10 -> 1.1 | E11: =Disclosures!E10 -> 1.5 | F11: =Disclosures!F10 -> 0.7 | G11: =Disclosures!G10 -> -0.3 | H11: =Disclosures!H10 -> -1.6 | I11: =Disclosures!I10 -> 2.5 | J11: =Disclosures!J10 -> -5.5 | K11: =Disclosures!K10 -> 1.3 | ... Q11: =Disclosures!Q10 -> 8.7 | R11: =R10*Assumptions!R11 -> 2.536 | S11: =S10*Assumptions!S11 -> 2.5994 | T11: =T10*Assumptions!T11 -> 2.664385 | U11: =U10*Assumptions!U11 -> 2.7309946 | V11: =V10*Assumptions!V11 -> 2.7992695 | W11: =W10*Assumptions!W11 -> 2.8692512
C12: Investment performance | D12: =Disclosures!D11 -> 0.7 | E12: =Disclosures!E11 -> 4.4 | F12: =Disclosures!F11 -> 0.1 | G12: =Disclosures!G11 -> 4.5 | H12: =Disclosures!H11 -> 9.8 | I12: =Disclosures!I11 -> 1.3 | J12: =Disclosures!J11 -> 0.4 | K12: =Disclosures!K11 -> -0.6 | ... Q12: =Disclosures!Q11 -> 16.7 | R12: =R10*Assumptions!R18 -> 3.804 | S12: =S10*Assumptions!S18 -> 3.8991 | T12: =T10*Assumptions!T18 -> 3.9965775 | U12: =U10*Assumptions!U18 -> 4.0964919 | V12: =V10*Assumptions!V18 -> 4.1989042 | W12: =W10*Assumptions!W18 -> 4.3038768
C13: FX: allocated when annual split disclosed | D13: n/d | E13: n/d | F13: n/d | G13: n/d | H13: =Disclosures!E51*(Disclosures!H12-Disclosures!H14)/(SUM(Disclosures!H12:K12)-SUM(Disclosures!H14:K14)) -> 0 | I13: =Disclosures!E51*(Disclosures!I12-Disclosures!I14)/(SUM(Disclosures!H12:K12)-SUM(Disclosures!H14:K14)) -> -0.76 | J13: =Disclosures!E51*(Disclosures!J12-Disclosures!J14)/(SUM(Disclosures!H12:K12)-SUM(Disclosures!H14:K14)) -> 1.0523077 | K13: =Disclosures!E51*(Disclosures!K12-Disclosures!K14)/(SUM(Disclosures!H12:K12)-SUM(Disclosures!H14:K14)) -> -4.0923077 | L13: =Disclosures!F51*(Disclosures!L12-Disclosures!L14)/(SUM(Disclosures!L12:O12)-SUM(Disclosures!L14:O14)) -> 1.6209677 | M13: =Disclosures!F51*(Disclosures!M12-Disclosures!M14)/(SUM(Disclosures!L12:O12)-SUM(Disclosures!L14:O14)) -> 3.35 | N13: =Disclosures!F51*(Disclosures!N12-Disclosures!N14)/(SUM(Disclosures!L12:O12)-SUM(Disclosures!L14:O14)) -> 0.97258065 | O13: =Disclosures!F51*(Disclosures!O12-Disclosures!O14)/(SUM(Disclosures!L12:O12)-SUM(Disclosures!L14:O14)) -> 0.75645161 | P13: n/d | Q13: n/d | R13: =Assumptions!$D$67 -> 0 | S13: =Assumptions!$D$67 -> 0 | T13: =Assumptions!$D$67 -> 0 | U13: =Assumptions!$D$67 -> 0 | V13: =Assumptions!$D$67 -> 0 | W13: =Assumptions!$D$67 -> 0
C14: Acquisitions | D14: =Disclosures!D14 -> 0 | E14: =Disclosures!E14 -> 0 | F14: =Disclosures!F14 -> 10.8 | G14: =Disclosures!G14 -> 0 | H14: =Disclosures!H14 -> 0 | I14: =Disclosures!I14 -> 0 | J14: =Disclosures!J14 -> 0 | K14: =Disclosures!K14 -> 0 | ... Q14: =Disclosures!Q14 -> 0 | R14: =Assumptions!$D$67 -> 0 | S14: =Assumptions!$D$67 -> 0 | T14: =Assumptions!$D$67 -> 0 | U14: =Assumptions!$D$67 -> 0 | V14: =Assumptions!$D$67 -> 0 | W14: =Assumptions!$D$67 -> 0
C15: Realisations: allocated when disclosed | D15: n/d | E15: n/d | F15: n/d | G15: n/d | H15: =Disclosures!$E$52*Assumptions!$D$48 -> -0.525 | I15: =Disclosures!$E$52*Assumptions!$D$48 -> -0.525 | J15: =Disclosures!$E$52*Assumptions!$D$48 -> -0.525 | K15: =Disclosures!$E$52*Assumptions!$D$48 -> -0.525 | L15: n/d | M15: n/d | N15: n/d | O15: n/d | P15: n/d | Q15: n/d | R15: =Assumptions!$D$67 -> 0 | S15: =Assumptions!$D$67 -> 0 | T15: =Assumptions!$D$67 -> 0 | U15: =Assumptions!$D$67 -> 0 | V15: =Assumptions!$D$67 -> 0 | W15: =Assumptions!$D$67 -> 0
C16: Other, including unseparated FX / exits | D16: =Disclosures!D12-SUM(D13:D15) -> -0.4 | E16: =Disclosures!E12-SUM(E13:E15) -> 1.1 | F16: =Disclosures!F12-SUM(F13:F15) -> -2.1 | G16: =Disclosures!G12-SUM(G13:G15) -> 2.1 | H16: =Disclosures!H12-SUM(H13:H15) -> 0.525 | I16: =Disclosures!I12-SUM(I13:I15) -> -0.015 | J16: =Disclosures!J12-SUM(J13:J15) -> 1.2726923 | K16: =Disclosures!K12-SUM(K13:K15) -> -2.3826923 | ... Q16: =Disclosures!Q12-SUM(Q13:Q15) -> -0.5 | R16: =Assumptions!$D$67 -> 0 | S16: =Assumptions!$D$67 -> 0 | T16: =Assumptions!$D$67 -> 0 | U16: =Assumptions!$D$67 -> 0 | V16: =Assumptions!$D$67 -> 0 | W16: =Assumptions!$D$67 -> 0
C17: Closing fee-paying AUM | D17: =SUM(D10:D16) -> 144.7 | E17: =SUM(E10:E16) -> 151.7 | F17: =SUM(F10:F16) -> 161.2 | G17: =SUM(G10:G16) -> 167.5 | H17: =SUM(H10:H16) -> 175.7 | I17: =SUM(I10:I16) -> 178.2 | J17: =SUM(J10:J16) -> 174.9 | K17: =SUM(K10:K16) -> 168.6 | ... W17: =SUM(W10:W16) -> 294.09825
C18: Average AUM: opening / closing midpoint | D18: =AVERAGE(D10,D17) -> 144 | E18: =AVERAGE(E10,E17) -> 148.2 | F18: =AVERAGE(F10,F17) -> 156.45 | G18: =AVERAGE(G10,G17) -> 164.35 | H18: =AVERAGE(H10,H17) -> 171.6 | I18: =AVERAGE(I10,I17) -> 176.95 | J18: =AVERAGE(J10,J17) -> 176.55 | K18: =AVERAGE(K10,K17) -> 171.75 | ... W18: =AVERAGE(W10,W17) -> 290.51169
C19: Net flows / opening AUM | D19: =D11/D10 -> 0.0076762038 | E19: =E11/E10 -> 0.010366275 | F19: =F11/F10 -> 0.0046143705 | G19: =G11/G10 -> -0.0018610422 | H19: =H11/H10 -> -0.0095522388 | I19: =I11/I10 -> 0.014228799 | J19: =J11/J10 -> -0.030864198 | K19: =K11/K10 -> 0.0074328188 | ... W19: =W11/W10 -> 0.01
C20: Investment performance / opening AUM | D20: =D12/D10 -> 0.0048848569 | E20: =E12/E10 -> 0.03040774 | F20: =F12/F10 -> 0.00065919578 | G20: =G12/G10 -> 0.027915633 | H20: =H12/H10 -> 0.058507463 | I20: =I12/I10 -> 0.0073989755 | J20: =J12/J10 -> 0.0022446689 | K20: =K12/K10 -> -0.0034305317 | ... W20: =W12/W10 -> 0.015
C23: REVENUE | RECURRING FEES AND VARIABLE FEES
C24: Gross management fees: historical memo | D24: =D27-D25 -> 234.57906 | E24: =E27-E25 -> 241.42094 | F24: =F27-F25 -> 253.10957 | G24: =G27-G25 -> 265.89043 | H24: =H27-H25 -> 279.6408 | I24: =I27-I25 -> 288.3592 | J24: =J27-J25 -> 287.40698 | K24: =K27-K25 -> 279.59302 | ... Q24: =Q27-Q25 -> 344.27978 | R24: n/a | S24: n/a | T24: n/a | U24: n/a | V24: n/a | W24: n/a
C25: Distribution costs: historical memo | D25: =-D82*D63 -> -7.8850103 | E25: =-E82*E63 -> -8.1149897 | F25: =-F82*F63 -> -7.8029925 | G25: =-G82*G63 -> -8.1970075 | H25: =-H82*H63 -> -8.3695309 | I25: =-I82*I63 -> -8.6304691 | J25: =-J82*J63 -> -10.644703 | K25: =-K82*K63 -> -10.355297 | ... Q25: =-Q82*Q63 -> -22.095568 | R25: n/a | S25: n/a | T25: n/a | U25: n/a | V25: n/a | W25: n/a
C26: Net management-fee margin, annual bp | D26: =D27/D18/Assumptions!$D$49/Assumptions!$D$48*Assumptions!$D$60 -> 62.970568 | E26: =E27/E18/Assumptions!$D$49/Assumptions!$D$48*Assumptions!$D$60 -> 62.970568 | F26: =F27/F18/Assumptions!$D$49/Assumptions!$D$48*Assumptions!$D$60 -> 62.718204 | G26: =G27/G18/Assumptions!$D$49/Assumptions!$D$48*Assumptions!$D$60 -> 62.718204 | H26: =H27/H18/Assumptions!$D$49/Assumptions!$D$48*Assumptions!$D$60 -> 63.233395 | I26: =I27/I18/Assumptions!$D$49/Assumptions!$D$48*Assumptions!$D$60 -> 63.233395 | J26: =J27/J18/Assumptions!$D$49/Assumptions!$D$48*Assumptions!$D$60 -> 62.704565 | K26: =K27/K18/Assumptions!$D$49/Assumptions!$D$48*Assumptions!$D$60 -> 62.704565 | ... Q26: =Q27/Q18/Assumptions!$D$49/Assumptions!$D$48*Assumptions!$D$60 -> 53.441296 | R26: =Assumptions!R25 -> 56 | S26: =Assumptions!S25 -> 56 | T26: =Assumptions!T25 -> 56 | U26: =Assumptions!U25 -> 56 | V26: =Assumptions!V25 -> 56 | W26: =Assumptions!W25 -> 56
C27: Net management fees | D27: =D65*D63 -> 226.69405 | E27: =E65*E63 -> 233.30595 | F27: =F65*F63 -> 245.30658 | G27: =G65*G63 -> 257.69342 | H27: =H65*H63 -> 271.27127 | I27: =I65*I63 -> 279.72873 | J27: =J65*J63 -> 276.76227 | K27: =K65*K63 -> 269.23773 | ... Q27: =Q65*Q63 -> 322.18421 | R27: =R18*Assumptions!$D$49*R26/Assumptions!$D$60*Assumptions!$D$48 -> 359.478 | S27: =S18*Assumptions!$D$49*S26/Assumptions!$D$60*Assumptions!$D$48 -> 368.46495 | T27: =T18*Assumptions!$D$49*T26/Assumptions!$D$60*Assumptions!$D$48 -> 377.67657 | U27: =U18*Assumptions!$D$49*U26/Assumptions!$D$60*Assumptions!$D$48 -> 387.11849 | V27: =V18*Assumptions!$D$49*V26/Assumptions!$D$60*Assumptions!$D$48 -> 396.79645 | W27: =W18*Assumptions!$D$49*W26/Assumptions!$D$60*Assumptions!$D$48 -> 406.71636
C28: Performance fees / carried interest | D28: =D66*D64 -> 3.2 | E28: =E66*E64 -> 28.8 | F28: =F66*F64 -> 14.8 | G28: =G66*G64 -> 133.2 | H28: =H66*H64 -> 17 | I28: =I66*I64 -> 153 | J28: =J66*J64 -> 14 | K28: =K66*K64 -> 126 | ... Q28: =Q66*Q64 -> 186.3 | R28: =Assumptions!R32 -> 21.4 | S28: =Assumptions!S32 -> 192.6 | T28: =Assumptions!T32 -> 6.7 | U28: =Assumptions!U32 -> 60.3 | V28: =Assumptions!V32 -> 21.4 | W28: =Assumptions!W32 -> 192.6
C29: Seed investment gains | D29: =D67*Assumptions!$D$43 -> 9.5 | E29: =E67*Assumptions!$D$43 -> 9.5 | F29: =F67*Assumptions!$D$43 -> 14.5 | G29: =G67*Assumptions!$D$43 -> 14.5 | H29: =H67*Assumptions!$D$43 -> 19.5 | I29: =I67*Assumptions!$D$43 -> 19.5 | J29: =J67*Assumptions!$D$43 -> 5.5 | K29: =K67*Assumptions!$D$43 -> 5.5 | ... Q29: =Q67*Assumptions!$D$43 -> 9 | R29: =Assumptions!$D$58 -> 9.5 | S29: =Assumptions!$D$58 -> 9.5 | T29: =Assumptions!$D$58 -> 9.5 | U29: =Assumptions!$D$58 -> 9.5 | V29: =Assumptions!$D$58 -> 9.5 | W29: =Assumptions!$D$58 -> 9.5
C30: Rental / other income | D30: =D73*Assumptions!$D$43 -> 1 | E30: =E73*Assumptions!$D$43 -> 1 | F30: =F73*Assumptions!$D$43 -> 1.5 | G30: =G73*Assumptions!$D$43 -> 1.5 | H30: =H73*Assumptions!$D$43 -> 0.5 | I30: =I73*Assumptions!$D$43 -> 0.5 | J30: =J73*Assumptions!$D$43 -> 0.5 | K30: =K73*Assumptions!$D$43 -> 0.5 | ... Q30: =Q73*Assumptions!$D$43 -> 0.5 | R30: =Assumptions!$D$59 -> 0.5 | S30: =Assumptions!$D$59 -> 0.5 | T30: =Assumptions!$D$59 -> 0.5 | U30: =Assumptions!$D$59 -> 0.5 | V30: =Assumptions!$D$59 -> 0.5 | W30: =Assumptions!$D$59 -> 0.5
C31: Core net revenue | D31: =SUM(D27:D30) -> 240.39405 | E31: =SUM(E27:E30) -> 272.60595 | F31: =SUM(F27:F30) -> 276.10658 | G31: =SUM(G27:G30) -> 406.89342 | H31: =SUM(H27:H30) -> 308.27127 | I31: =SUM(I27:I30) -> 452.72873 | J31: =SUM(J27:J30) -> 296.76227 | K31: =SUM(K27:K30) -> 401.23773 | ... W31: =SUM(W27:W30) -> 609.31636
C33: COSTS | FIXED CAPACITY AND VARIABLE PARTICIPATION
C34: Fixed compensation | D34: =-D68*Assumptions!$D$43 -> -59 | E34: =-E68*Assumptions!$D$43 -> -59 | F34: =-F68*Assumptions!$D$43 -> -60.5 | G34: =-G68*Assumptions!$D$43 -> -60.5 | H34: =-H68*Assumptions!$D$43 -> -67 | I34: =-I68*Assumptions!$D$43 -> -67 | J34: =-J68*Assumptions!$D$43 -> -65 | K34: =-K68*Assumptions!$D$43 -> -65 | ... Q34: =-Q68*Assumptions!$D$43 -> -71.5 | R34: =-Assumptions!$D$54 -> -68.5 | S34: =-Assumptions!$D$54 -> -68.5 | T34: =-Assumptions!$D$54 -> -68.5 | U34: =-Assumptions!$D$54 -> -68.5 | V34: =-Assumptions!$D$54 -> -68.5 | W34: =-Assumptions!$D$54 -> -68.5
C35: Variable management compensation | D35: =-(D69-D68)*D63 -> -47.802875 | E35: =-(E69-E68)*E63 -> -49.197125 | F35: =-(F69-F68)*F63 -> -50.231764 | G35: =-(G69-G68)*G63 -> -52.768236 | H35: =-(H69-H68)*H63 -> -57.602066 | I35: =-(I69-I68)*I63 -> -59.397934 | J35: =-(J69-J68)*J63 -> -55.251077 | K35: =-(K69-K68)*K63 -> -53.748923 | ... Q35: =-(Q69-Q68)*Q63 -> -71.425208 | R35: =-R27*Assumptions!$D$51 -> -69.091872 | S35: =-S27*Assumptions!$D$51 -> -70.819169 | T35: =-T27*Assumptions!$D$51 -> -72.589648 | U35: =-U27*Assumptions!$D$51 -> -74.404389 | V35: =-V27*Assumptions!$D$51 -> -76.264499 | W35: =-W27*Assumptions!$D$51 -> -78.171111
C36: Variable performance-fee compensation | D36: =-D70*D28/SUM(D66:D67) -> -2.6352941 | E36: =-E70*E28/SUM(E66:E67) -> -23.717647 | F36: =-F70*F28/SUM(F66:F67) -> -9.5322034 | G36: =-G70*G28/SUM(G66:G67) -> -85.789831 | H36: =-H70*H28/SUM(H66:H67) -> -8.7033493 | I36: =-I70*I28/SUM(I66:I67) -> -78.330144 | J36: =-J70*J28/SUM(J66:J67) -> -8.0662252 | K36: =-K70*K28/SUM(K66:K67) -> -72.596026 | ... Q36: =-Q70*Q28/SUM(Q66:Q67) -> -90.252 | R36: =-R28*Assumptions!$D$52 -> -13.01442 | S36: =-S28*Assumptions!$D$52 -> -117.12978 | T36: =-T28*Assumptions!$D$52 -> -4.0746082 | U36: =-U28*Assumptions!$D$52 -> -36.671473 | V36: =-V28*Assumptions!$D$52 -> -13.01442 | W36: =-W28*Assumptions!$D$52 -> -117.12978
C37: Variable seed-gain compensation | D37: =-D70*D29/SUM(D66:D67) -> -7.8235294 | E37: =-E70*E29/SUM(E66:E67) -> -7.8235294 | F37: =-F70*F29/SUM(F66:F67) -> -9.3389831 | G37: =-G70*G29/SUM(G66:G67) -> -9.3389831 | H37: =-H70*H29/SUM(H66:H67) -> -9.9832536 | I37: =-I70*I29/SUM(I66:I67) -> -9.9832536 | J37: =-J70*J29/SUM(J66:J67) -> -3.1688742 | K37: =-K70*K29/SUM(K66:K67) -> -3.1688742 | ... Q37: =-Q70*Q29/SUM(Q66:Q67) -> -4.36 | R37: =-R29*Assumptions!$D$52 -> -5.7774295 | S37: =-S29*Assumptions!$D$52 -> -5.7774295 | T37: =-T29*Assumptions!$D$52 -> -5.7774295 | U37: =-U29*Assumptions!$D$52 -> -5.7774295 | V37: =-V29*Assumptions!$D$52 -> -5.7774295 | W37: =-W29*Assumptions!$D$52 -> -5.7774295
C38: Total core compensation | D38: =SUM(D34:D37) -> -117.2617 | E38: =SUM(E34:E37) -> -139.7383 | F38: =SUM(F34:F37) -> -129.60295 | G38: =SUM(G34:G37) -> -208.39705 | H38: =SUM(H34:H37) -> -143.28867 | I38: =SUM(I34:I37) -> -214.71133 | J38: =SUM(J34:J37) -> -131.48618 | K38: =SUM(K34:K37) -> -194.51382 | ... W38: =SUM(W34:W37) -> -269.57832
C39: Asset servicing costs | D39: =-D72*D63 -> -13.305955 | E39: =-E72*E63 -> -13.694045 | F39: =-F72*F63 -> -15.118298 | G39: =-G72*G63 -> -15.881702 | H39: =-H72*H63 -> -16.246736 | I39: =-I72*I63 -> -16.753264 | J39: =-J72*J63 -> -17.234281 | K39: =-K72*K63 -> -16.765719 | ... Q39: =-Q72*Q63 -> -20.040166 | R39: =-R18*Assumptions!$D$49*Assumptions!$D$53/Assumptions!$D$60*Assumptions!$D$48 -> -24.095912 | S39: =-S18*Assumptions!$D$49*Assumptions!$D$53/Assumptions!$D$60*Assumptions!$D$48 -> -24.69831 | T39: =-T18*Assumptions!$D$49*Assumptions!$D$53/Assumptions!$D$60*Assumptions!$D$48 -> -25.315768 | U39: =-U18*Assumptions!$D$49*Assumptions!$D$53/Assumptions!$D$60*Assumptions!$D$48 -> -25.948662 | V39: =-V18*Assumptions!$D$49*Assumptions!$D$53/Assumptions!$D$60*Assumptions!$D$48 -> -26.597378 | W39: =-W18*Assumptions!$D$49*Assumptions!$D$53/Assumptions!$D$60*Assumptions!$D$48 -> -27.262313
C40: Other fixed costs, including D&A | D40: =-D71*Assumptions!$D$43 -> -43 | E40: =-E71*Assumptions!$D$43 -> -43 | F40: =-F71*Assumptions!$D$43 -> -46.5 | G40: =-G71*Assumptions!$D$43 -> -46.5 | H40: =-H71*Assumptions!$D$43 -> -46.5 | I40: =-I71*Assumptions!$D$43 -> -46.5 | J40: =-J71*Assumptions!$D$43 -> -53 | K40: =-K71*Assumptions!$D$43 -> -53 | ... Q40: =-Q71*Assumptions!$D$43 -> -56.5 | R40: =-Assumptions!$D$55 -> -53.75 | S40: =-Assumptions!$D$55 -> -53.75 | T40: =-Assumptions!$D$55 -> -53.75 | U40: =-Assumptions!$D$55 -> -53.75 | V40: =-Assumptions!$D$55 -> -53.75 | W40: =-Assumptions!$D$55 -> -53.75
C41: Other employment-related expenses | D41: =-D74*Assumptions!$D$43 -> 0 | E41: =-E74*Assumptions!$D$43 -> 0 | F41: =-F74*Assumptions!$D$43 -> -1 | G41: =-G74*Assumptions!$D$43 -> -1 | H41: =-H74*Assumptions!$D$43 -> -1.5 | I41: =-I74*Assumptions!$D$43 -> -1.5 | J41: =-J74*Assumptions!$D$43 -> -3.5 | K41: =-K74*Assumptions!$D$43 -> -3.5 | ... Q41: =-Q74*Assumptions!$D$43 -> -1.5 | R41: =-Assumptions!$D$62 -> -1.75 | S41: =-Assumptions!$D$62 -> -1.75 | T41: =-Assumptions!$D$62 -> -1.75 | U41: =-Assumptions!$D$62 -> -1.75 | V41: =-Assumptions!$D$62 -> -1.75 | W41: =-Assumptions!$D$62 -> -1.75
C42: Total core operating costs | D42: =SUM(D38:D41) -> -173.56765 | E42: =SUM(E38:E41) -> -196.43235 | F42: =SUM(F38:F41) -> -192.22125 | G42: =SUM(G38:G41) -> -271.77875 | H42: =SUM(H38:H41) -> -207.53541 | I42: =SUM(I38:I41) -> -279.46459 | J42: =SUM(J38:J41) -> -205.22046 | K42: =SUM(K38:K41) -> -267.77954 | ... W42: =SUM(W38:W41) -> -352.34063
C43: Core operating profit before seed gains | D43: =SUM(D27:D28,D30,D42) -> 57.326392 | E43: =SUM(E27:E28,E30,E42) -> 66.673608 | F43: =SUM(F27:F28,F30,F42) -> 69.385329 | G43: =SUM(G27:G28,G30,G42) -> 120.61467 | H43: =SUM(H27:H28,H30,H42) -> 81.235862 | I43: =SUM(I27:I28,I30,I42) -> 153.76414 | J43: =SUM(J27:J28,J30,J42) -> 86.041817 | K43: =SUM(K27:K28,K30,K42) -> 127.95818 | ... W43: =SUM(W27:W28,W30,W42) -> 247.47573
C44: Core operating profit including seed gains | D44: =SUM(D31,D42) -> 66.826392 | E44: =SUM(E31,E42) -> 76.173608 | F44: =SUM(F31,F42) -> 83.885329 | G44: =SUM(G31,G42) -> 135.11467 | H44: =SUM(H31,H42) -> 100.73586 | I44: =SUM(I31,I42) -> 173.26414 | J44: =SUM(J31,J42) -> 91.541817 | K44: =SUM(K31,K42) -> 133.45818 | ... W44: =SUM(W31,W42) -> 256.97573
C46: PROFIT | FUNDING, TAX AND DILUTED SHARES
C47: Management-fee finance expense | D47: =-D75*Assumptions!$D$43 -> -0.5 | E47: =-E75*Assumptions!$D$43 -> -0.5 | F47: =-F75*Assumptions!$D$43 -> -4 | G47: =-G75*Assumptions!$D$43 -> -4 | H47: =-H75*Assumptions!$D$43 -> -4 | I47: =-I75*Assumptions!$D$43 -> -4 | J47: =-J75*Assumptions!$D$43 -> 0 | K47: =-K75*Assumptions!$D$43 -> 0 | ... Q47: =-Q75*Assumptions!$D$43 -> -2 | R47: =-Assumptions!$D$63 -> -1.75 | S47: =-Assumptions!$D$63 -> -1.75 | T47: =-Assumptions!$D$63 -> -1.75 | U47: =-Assumptions!$D$63 -> -1.75 | V47: =-Assumptions!$D$63 -> -1.75 | W47: =-Assumptions!$D$63 -> -1.75
C48: Performance / seed finance expense | D48: =-D76*Assumptions!$D$43 -> -2.5 | E48: =-E76*Assumptions!$D$43 -> -2.5 | F48: =-F76*Assumptions!$D$43 -> -3.5 | G48: =-G76*Assumptions!$D$43 -> -3.5 | H48: =-H76*Assumptions!$D$43 -> -3.5 | I48: =-I76*Assumptions!$D$43 -> -3.5 | J48: =-J76*Assumptions!$D$43 -> -4 | K48: =-K76*Assumptions!$D$43 -> -4 | ... Q48: =-Q76*Assumptions!$D$43 -> -2.5 | R48: =-Assumptions!$D$64 -> -2.75 | S48: =-Assumptions!$D$64 -> -2.75 | T48: =-Assumptions!$D$64 -> -2.75 | U48: =-Assumptions!$D$64 -> -2.75 | V48: =-Assumptions!$D$64 -> -2.75 | W48: =-Assumptions!$D$64 -> -2.75
C49: Third-party profit share: management | D49: =-D77*Assumptions!$D$43 -> 0 | E49: =-E77*Assumptions!$D$43 -> 0 | F49: =-F77*Assumptions!$D$43 -> -0.5 | G49: =-G77*Assumptions!$D$43 -> -0.5 | H49: =-H77*Assumptions!$D$43 -> -0.5 | I49: =-I77*Assumptions!$D$43 -> -0.5 | J49: =-J77*Assumptions!$D$43 -> -0.5 | K49: =-K77*Assumptions!$D$43 -> -0.5 | ... Q49: =-Q77*Assumptions!$D$43 -> -0.5 | R49: =-Assumptions!$D$65 -> -0.5 | S49: =-Assumptions!$D$65 -> -0.5 | T49: =-Assumptions!$D$65 -> -0.5 | U49: =-Assumptions!$D$65 -> -0.5 | V49: =-Assumptions!$D$65 -> -0.5 | W49: =-Assumptions!$D$65 -> -0.5
C50: Third-party profit share: performance | D50: =-D78*D64 -> 0 | E50: =-E78*E64 -> 0 | F50: =-F78*F64 -> 0 | G50: =-G78*G64 -> 0 | H50: =-H78*H64 -> -0.1 | I50: =-I78*I64 -> -0.9 | J50: =-J78*J64 -> 0 | K50: =-K78*K64 -> 0 | ... Q50: =-Q78*Q64 -> 0 | R50: =-R28*Assumptions!$D$66 -> -0.076156584 | S50: =-S28*Assumptions!$D$66 -> -0.68540925 | T50: =-T28*Assumptions!$D$66 -> -0.023843416 | U50: =-U28*Assumptions!$D$66 -> -0.21459075 | V50: =-V28*Assumptions!$D$66 -> -0.076156584 | W50: =-W28*Assumptions!$D$66 -> -0.68540925
C51: Core management-fee profit before tax | D51: =SUM(D27,D30,D34:D35,D39:D41,D47,D49) -> 64.085216 | E51: =SUM(E27,E30,E34:E35,E39:E41,E47,E49) -> 68.914784 | F51: =SUM(F27,F30,F34:F35,F39:F41,F47,F49) -> 68.956515 | G51: =SUM(G27,G30,G34:G35,G39:G41,G47,G49) -> 78.043485 | H51: =SUM(H27,H30,H34:H35,H39:H41,H47,H49) -> 78.422464 | I51: =SUM(I27,I30,I34:I35,I39:I41,I47,I49) -> 84.577536 | J51: =SUM(J27,J30,J34:J35,J39:J41,J47,J49) -> 82.776916 | K51: =SUM(K27,K30,K34:K35,K39:K41,K47,K49) -> 77.223084 | ... W51: =SUM(W27,W30,W34:W35,W39:W41,W47,W49) -> 175.53294
C52: Core performance / seed profit before tax | D52: =SUM(D28:D29,D36:D37,D48,D50) -> -0.25882353 | E52: =SUM(E28:E29,E36:E37,E48,E50) -> 4.2588235 | F52: =SUM(F28:F29,F36:F37,F48,F50) -> 6.9288136 | G52: =SUM(G28:G29,G36:G37,G48,G50) -> 49.071186 | H52: =SUM(H28:H29,H36:H37,H48,H50) -> 14.213397 | I52: =SUM(I28:I29,I36:I37,I48,I50) -> 79.786603 | J52: =SUM(J28:J29,J36:J37,J48,J50) -> 4.2649007 | K52: =SUM(K28:K29,K36:K37,K48,K50) -> 51.735099 | ... W52: =SUM(W28:W29,W36:W37,W48,W50) -> 75.757381
C53: Core total profit before tax | D53: =SUM(D51:D52) -> 63.826392 | E53: =SUM(E51:E52) -> 73.173608 | F53: =SUM(F51:F52) -> 75.885329 | G53: =SUM(G51:G52) -> 127.11467 | H53: =SUM(H51:H52) -> 92.635862 | I53: =SUM(I51:I52) -> 164.36414 | J53: =SUM(J51:J52) -> 87.041817 | K53: =SUM(K51:K52) -> 128.95818 | ... W53: =SUM(W51:W52) -> 251.29032
C54: Core tax expense | D54: =-D53*D79/D80 -> -13.510696 | E54: =-E53*E79/E80 -> -15.489304 | F54: =-F53*F79/F80 -> -14.952774 | G54: =-G53*G79/G80 -> -25.047226 | H54: =-H53*H79/H80 -> -19.103894 | I54: =-I53*I79/I80 -> -33.896106 | J54: =-J53*J79/J80 -> -15.715884 | K54: =-K53*K79/K80 -> -23.284116 | ... Q54: =-Q53*Q79/Q80 -> -44.532855 | R54: =-R53*Assumptions!$D$56 -> -31.657764 | S54: =-S53*Assumptions!$D$56 -> -47.110853 | T54: =-T53*Assumptions!$D$56 -> -33.300231 | U54: =-U53*Assumptions!$D$56 -> -39.175841 | V54: =-V53*Assumptions!$D$56 -> -37.499078 | W54: =-W53*Assumptions!$D$56 -> -53.0982
C55: Core profit after tax | D55: =SUM(D53:D54) -> 50.315696 | E55: =SUM(E53:E54) -> 57.684304 | F55: =SUM(F53:F54) -> 60.932554 | G55: =SUM(G53:G54) -> 102.06745 | H55: =SUM(H53:H54) -> 73.531968 | I55: =SUM(I53:I54) -> 130.46803 | J55: =SUM(J53:J54) -> 71.325933 | K55: =SUM(K53:K54) -> 105.67407 | ... W55: =SUM(W53:W54) -> 198.19212
C56: Diluted weighted average shares, m | D56: =D81 -> 1217 | E56: =E81 -> 1217 | F56: =F81 -> 1197.273 | G56: =G81 -> 1197.273 | H56: =H81 -> 1192 | I56: =I81 -> 1192 | J56: =J81 -> 1186.1835 | K56: =K81 -> 1186.1835 | ... Q56: =Q81 -> 1153 | R56: =Assumptions!$D$57 -> 1164.8774 | S56: =Assumptions!$D$57 -> 1164.8774 | T56: =Assumptions!$D$57 -> 1164.8774 | U56: =Assumptions!$D$57 -> 1164.8774 | V56: =Assumptions!$D$57 -> 1164.8774 | W56: =Assumptions!$D$57 -> 1164.8774
C57: Core diluted EPS, US cents | D57: =D55/D56*Assumptions!$D$61 -> 4.1344039 | E57: =E55/E56*Assumptions!$D$61 -> 4.7398771 | F57: =F55/F56*Assumptions!$D$61 -> 5.0892782 | G57: =G55/G56*Assumptions!$D$61 -> 8.5249933 | H57: =H55/H56*Assumptions!$D$61 -> 6.1687893 | I57: =I55/I56*Assumptions!$D$61 -> 10.945305 | J57: =J55/J56*Assumptions!$D$61 -> 6.0130608 | K57: =K55/K56*Assumptions!$D$61 -> 8.9087455 | ... W57: =W55/W56*Assumptions!$D$61 -> 17.01399
C58: Core operating margin | D58: =D44/D31 -> 0.27798689 | E58: =E44/E31 -> 0.27942753 | F58: =F44/F31 -> 0.30381503 | G58: =G44/G31 -> 0.33206403 | H58: =H44/H31 -> 0.32677668 | I58: =I44/I31 -> 0.38271072 | J58: =J44/J31 -> 0.30846851 | K58: =K44/K31 -> 0.33261624 | ... W58: =W44/W31 -> 0.42174434
C59: Performance fees / net revenue | D59: =D28/D31 -> 0.013311478 | E59: =E28/E31 -> 0.105647 | F59: =F28/F31 -> 0.05360249 | G59: =G28/G31 -> 0.32735845 | H59: =H28/H31 -> 0.055146236 | I59: =I28/I31 -> 0.33795072 | J59: =J28/J31 -> 0.047175808 | K59: =K28/K31 -> 0.3140283 | ... W59: =W28/W31 -> 0.31609196
C60: Core effective tax rate | D60: =-D54/D53 -> 0.21167883 | E60: =-E54/E53 -> 0.21167883 | F60: =-F54/F53 -> 0.19704433 | G60: =-G54/G53 -> 0.19704433 | H60: =-H54/H53 -> 0.20622568 | I60: =-I54/I53 -> 0.20622568 | J60: =-J54/J53 -> 0.18055556 | K60: =-K54/K53 -> 0.18055556 | ... W60: =-W54/W53 -> 0.21130221
C62: HISTORICAL ALLOCATION | H1 AND FY LESS H1
C63: Quarter share of half-year midpoint AUM | D63: =D18/SUM(D18:E18) -> 0.49281314 | E63: =E18/SUM(D18:E18) -> 0.50718686 | F63: =F18/SUM(F18:G18) -> 0.48768703 | G63: =G18/SUM(F18:G18) -> 0.51231297 | H63: =H18/SUM(H18:I18) -> 0.49232535 | I63: =I18/SUM(H18:I18) -> 0.50767465 | J63: =J18/SUM(J18:K18) -> 0.50689061 | K63: =K18/SUM(J18:K18) -> 0.49310939 | L63: =L18/SUM(L18:M18) -> 0.4825343 | M63: =M18/SUM(L18:M18) -> 0.5174657 | N63: =N18/SUM(N18:O18) -> 0.47979262 | O63: =O18/SUM(N18:O18) -> 0.52020738 | P63: =P18/SUM(P18:Q18) -> 0.48614958 | Q63: =Q18/SUM(P18:Q18) -> 0.51385042
C64: Quarter share of half-year PF revenue | D64: =Assumptions!$D$41 -> 0.1 | E64: =1-Assumptions!$D$41 -> 0.9 | F64: =Assumptions!$D$42 -> 0.1 | G64: =1-Assumptions!$D$42 -> 0.9 | H64: =Assumptions!$D$41 -> 0.1 | I64: =1-Assumptions!$D$41 -> 0.9 | J64: =Assumptions!$D$42 -> 0.1 | K64: =1-Assumptions!$D$42 -> 0.9 | L64: =Assumptions!$D$41 -> 0.1 | M64: =1-Assumptions!$D$41 -> 0.9 | N64: =Assumptions!$D$42 -> 0.1 | O64: =1-Assumptions!$D$42 -> 0.9 | P64: =Assumptions!$D$41 -> 0.1 | Q64: =1-Assumptions!$D$41 -> 0.9
C65: Half-year net management fees | D65: =Disclosures!D22 -> 460 | E65: =Disclosures!D22 -> 460 | F65: =Disclosures!E22-Disclosures!D22 -> 503 | G65: =Disclosures!E22-Disclosures!D22 -> 503 | H65: =Disclosures!F22 -> 551 | I65: =Disclosures!F22 -> 551 | J65: =Disclosures!G22-Disclosures!F22 -> 546 | K65: =Disclosures!G22-Disclosures!F22 -> 546 | L65: =Disclosures!H22 -> 517 | M65: =Disclosures!H22 -> 517 | N65: =Disclosures!I22-Disclosures!H22 -> 560 | O65: =Disclosures!I22-Disclosures!H22 -> 560 | P65: =Disclosures!J22 -> 627 | Q65: =Disclosures!J22 -> 627
C66: Half-year performance fees | D66: =Disclosures!D23 -> 32 | E66: =Disclosures!D23 -> 32 | F66: =Disclosures!E23-Disclosures!D23 -> 148 | G66: =Disclosures!E23-Disclosures!D23 -> 148 | H66: =Disclosures!F23 -> 170 | I66: =Disclosures!F23 -> 170 | J66: =Disclosures!G23-Disclosures!F23 -> 140 | K66: =Disclosures!G23-Disclosures!F23 -> 140 | L66: =Disclosures!H23 -> 67 | M66: =Disclosures!H23 -> 67 | N66: =Disclosures!I23-Disclosures!H23 -> 214 | O66: =Disclosures!I23-Disclosures!H23 -> 214 | P66: =Disclosures!J23 -> 207 | Q66: =Disclosures!J23 -> 207
C67: Half-year seed gains | D67: =Disclosures!D24 -> 19 | E67: =Disclosures!D24 -> 19 | F67: =Disclosures!E24-Disclosures!D24 -> 29 | G67: =Disclosures!E24-Disclosures!D24 -> 29 | H67: =Disclosures!F24 -> 39 | I67: =Disclosures!F24 -> 39 | J67: =Disclosures!G24-Disclosures!F24 -> 11 | K67: =Disclosures!G24-Disclosures!F24 -> 11 | L67: =Disclosures!H24 -> 19 | M67: =Disclosures!H24 -> 19 | N67: =Disclosures!I24-Disclosures!H24 -> 19 | O67: =Disclosures!I24-Disclosures!H24 -> 19 | P67: =Disclosures!J24 -> 18 | Q67: =Disclosures!J24 -> 18
C68: Half-year fixed compensation | D68: =Disclosures!D27 -> 118 | E68: =Disclosures!D27 -> 118 | F68: =Disclosures!E27-Disclosures!D27 -> 121 | G68: =Disclosures!E27-Disclosures!D27 -> 121 | H68: =Disclosures!F27 -> 134 | I68: =Disclosures!F27 -> 134 | J68: =Disclosures!G27-Disclosures!F27 -> 130 | K68: =Disclosures!G27-Disclosures!F27 -> 130 | L68: =Disclosures!H27 -> 141 | M68: =Disclosures!H27 -> 141 | N68: =Disclosures!I27-Disclosures!H27 -> 133 | O68: =Disclosures!I27-Disclosures!H27 -> 133 | P68: =Disclosures!J27 -> 143 | Q68: =Disclosures!J27 -> 143
C69: Half-year management compensation | D69: =Disclosures!D28 -> 215 | E69: =Disclosures!D28 -> 215 | F69: =Disclosures!E28-Disclosures!D28 -> 224 | G69: =Disclosures!E28-Disclosures!D28 -> 224 | H69: =Disclosures!F28 -> 251 | I69: =Disclosures!F28 -> 251 | J69: =Disclosures!G28-Disclosures!F28 -> 239 | K69: =Disclosures!G28-Disclosures!F28 -> 239 | L69: =Disclosures!H28 -> 239 | M69: =Disclosures!H28 -> 239 | N69: =Disclosures!I28-Disclosures!H28 -> 242 | O69: =Disclosures!I28-Disclosures!H28 -> 242 | P69: =Disclosures!J28 -> 282 | Q69: =Disclosures!J28 -> 282
C70: Half-year performance compensation | D70: =Disclosures!D29 -> 42 | E70: =Disclosures!D29 -> 42 | F70: =Disclosures!E29-Disclosures!D29 -> 114 | G70: =Disclosures!E29-Disclosures!D29 -> 114 | H70: =Disclosures!F29 -> 107 | I70: =Disclosures!F29 -> 107 | J70: =Disclosures!G29-Disclosures!F29 -> 87 | K70: =Disclosures!G29-Disclosures!F29 -> 87 | L70: =Disclosures!H29 -> 63 | M70: =Disclosures!H29 -> 63 | N70: =Disclosures!I29-Disclosures!H29 -> 131 | O70: =Disclosures!I29-Disclosures!H29 -> 131 | P70: =Disclosures!J29 -> 109 | Q70: =Disclosures!J29 -> 109
C71: Half-year other costs | D71: =Disclosures!D30 -> 86 | E71: =Disclosures!D30 -> 86 | F71: =Disclosures!E30-Disclosures!D30 -> 93 | G71: =Disclosures!E30-Disclosures!D30 -> 93 | H71: =Disclosures!F30 -> 93 | I71: =Disclosures!F30 -> 93 | J71: =Disclosures!G30-Disclosures!F30 -> 106 | K71: =Disclosures!G30-Disclosures!F30 -> 106 | L71: =Disclosures!H30 -> 110 | M71: =Disclosures!H30 -> 110 | N71: =Disclosures!I30-Disclosures!H30 -> 105 | O71: =Disclosures!I30-Disclosures!H30 -> 105 | P71: =Disclosures!J30 -> 113 | Q71: =Disclosures!J30 -> 113
C72: Half-year servicing | D72: =Disclosures!D26 -> 27 | E72: =Disclosures!D26 -> 27 | F72: =Disclosures!E26-Disclosures!D26 -> 31 | G72: =Disclosures!E26-Disclosures!D26 -> 31 | H72: =Disclosures!F26 -> 33 | I72: =Disclosures!F26 -> 33 | J72: =Disclosures!G26-Disclosures!F26 -> 34 | K72: =Disclosures!G26-Disclosures!F26 -> 34 | L72: =Disclosures!H26 -> 35 | M72: =Disclosures!H26 -> 35 | N72: =Disclosures!I26-Disclosures!H26 -> 38 | O72: =Disclosures!I26-Disclosures!H26 -> 38 | P72: =Disclosures!J26 -> 39 | Q72: =Disclosures!J26 -> 39
C73: Half-year rental / other income | D73: =Disclosures!D25 -> 2 | E73: =Disclosures!D25 -> 2 | F73: =Disclosures!E25-Disclosures!D25 -> 3 | G73: =Disclosures!E25-Disclosures!D25 -> 3 | H73: =Disclosures!F25 -> 1 | I73: =Disclosures!F25 -> 1 | J73: =Disclosures!G25-Disclosures!F25 -> 1 | K73: =Disclosures!G25-Disclosures!F25 -> 1 | L73: =Disclosures!H25 -> 1 | M73: =Disclosures!H25 -> 1 | N73: =Disclosures!I25-Disclosures!H25 -> 1 | O73: =Disclosures!I25-Disclosures!H25 -> 1 | P73: =Disclosures!J25 -> 1 | Q73: =Disclosures!J25 -> 1
C74: Half-year other employment | D74: =Disclosures!D31 -> 0 | E74: =Disclosures!D31 -> 0 | F74: =Disclosures!E31-Disclosures!D31 -> 2 | G74: =Disclosures!E31-Disclosures!D31 -> 2 | H74: =Disclosures!F31 -> 3 | I74: =Disclosures!F31 -> 3 | J74: =Disclosures!G31-Disclosures!F31 -> 7 | K74: =Disclosures!G31-Disclosures!F31 -> 7 | L74: =Disclosures!H31 -> 2 | M74: =Disclosures!H31 -> 2 | N74: =Disclosures!I31-Disclosures!H31 -> 5 | O74: =Disclosures!I31-Disclosures!H31 -> 5 | P74: =Disclosures!J31 -> 3 | Q74: =Disclosures!J31 -> 3
C75: Half-year management finance expense | D75: =Disclosures!D32 -> 1 | E75: =Disclosures!D32 -> 1 | F75: =Disclosures!E32-Disclosures!D32 -> 8 | G75: =Disclosures!E32-Disclosures!D32 -> 8 | H75: =Disclosures!F32 -> 8 | I75: =Disclosures!F32 -> 8 | J75: =Disclosures!G32-Disclosures!F32 -> 0 | K75: =Disclosures!G32-Disclosures!F32 -> 0 | L75: =Disclosures!H32 -> 1 | M75: =Disclosures!H32 -> 1 | N75: =Disclosures!I32-Disclosures!H32 -> 6 | O75: =Disclosures!I32-Disclosures!H32 -> 6 | P75: =Disclosures!J32 -> 4 | Q75: =Disclosures!J32 -> 4
C76: Half-year performance finance expense | D76: =Disclosures!D33 -> 5 | E76: =Disclosures!D33 -> 5 | F76: =Disclosures!E33-Disclosures!D33 -> 7 | G76: =Disclosures!E33-Disclosures!D33 -> 7 | H76: =Disclosures!F33 -> 7 | I76: =Disclosures!F33 -> 7 | J76: =Disclosures!G33-Disclosures!F33 -> 8 | K76: =Disclosures!G33-Disclosures!F33 -> 8 | L76: =Disclosures!H33 -> 7 | M76: =Disclosures!H33 -> 7 | N76: =Disclosures!I33-Disclosures!H33 -> 4 | O76: =Disclosures!I33-Disclosures!H33 -> 4 | P76: =Disclosures!J33 -> 5 | Q76: =Disclosures!J33 -> 5
C77: Half-year management third-party share | D77: =Disclosures!D34 -> 0 | E77: =Disclosures!D34 -> 0 | F77: =Disclosures!E34-Disclosures!D34 -> 1 | G77: =Disclosures!E34-Disclosures!D34 -> 1 | H77: =Disclosures!F34 -> 1 | I77: =Disclosures!F34 -> 1 | J77: =Disclosures!G34-Disclosures!F34 -> 1 | K77: =Disclosures!G34-Disclosures!F34 -> 1 | L77: =Disclosures!H34 -> 1 | M77: =Disclosures!H34 -> 1 | N77: =Disclosures!I34-Disclosures!H34 -> 1 | O77: =Disclosures!I34-Disclosures!H34 -> 1 | P77: =Disclosures!J34 -> 1 | Q77: =Disclosures!J34 -> 1
C78: Half-year performance third-party share | D78: =Disclosures!D35 -> 0 | E78: =Disclosures!D35 -> 0 | F78: =Disclosures!E35-Disclosures!D35 -> 0 | G78: =Disclosures!E35-Disclosures!D35 -> 0 | H78: =Disclosures!F35 -> 1 | I78: =Disclosures!F35 -> 1 | J78: =Disclosures!G35-Disclosures!F35 -> 0 | K78: =Disclosures!G35-Disclosures!F35 -> 0 | L78: =Disclosures!H35 -> 0 | M78: =Disclosures!H35 -> 0 | N78: =Disclosures!I35-Disclosures!H35 -> 1 | O78: =Disclosures!I35-Disclosures!H35 -> 1 | P78: =Disclosures!J35 -> 0 | Q78: =Disclosures!J35 -> 0
C79: Half-year core tax expense | D79: =Disclosures!D39 -> 29 | E79: =Disclosures!D39 -> 29 | F79: =Disclosures!E39-Disclosures!D39 -> 40 | G79: =Disclosures!E39-Disclosures!D39 -> 40 | H79: =Disclosures!F39 -> 53 | I79: =Disclosures!F39 -> 53 | J79: =Disclosures!G39-Disclosures!F39 -> 39 | K79: =Disclosures!G39-Disclosures!F39 -> 39 | L79: =Disclosures!H39 -> 33 | M79: =Disclosures!H39 -> 33 | N79: =Disclosures!I39-Disclosures!H39 -> 53 | O79: =Disclosures!I39-Disclosures!H39 -> 53 | P79: =Disclosures!J39 -> 67 | Q79: =Disclosures!J39 -> 67
C80: Half-year core PBT | D80: =Disclosures!D38 -> 137 | E80: =Disclosures!D38 -> 137 | F80: =Disclosures!E38-Disclosures!D38 -> 203 | G80: =Disclosures!E38-Disclosures!D38 -> 203 | H80: =Disclosures!F38 -> 257 | I80: =Disclosures!F38 -> 257 | J80: =Disclosures!G38-Disclosures!F38 -> 216 | K80: =Disclosures!G38-Disclosures!F38 -> 216 | L80: =Disclosures!H38 -> 146 | M80: =Disclosures!H38 -> 146 | N80: =Disclosures!I38-Disclosures!H38 -> 261 | O80: =Disclosures!I38-Disclosures!H38 -> 261 | P80: =Disclosures!J38 -> 297 | Q80: =Disclosures!J38 -> 297
C81: Half-year diluted weighted shares | D81: =Disclosures!D41 -> 1217 | E81: =Disclosures!D41 -> 1217 | F81: =(Disclosures!E41*365-Disclosures!D41*181)/184 -> 1197.273 | G81: =(Disclosures!E41*365-Disclosures!D41*181)/184 -> 1197.273 | H81: =Disclosures!F41 -> 1192 | I81: =Disclosures!F41 -> 1192 | J81: =(Disclosures!G41*366-Disclosures!F41*182)/184 -> 1186.1835 | K81: =(Disclosures!G41*366-Disclosures!F41*182)/184 -> 1186.1835 | L81: =Disclosures!H41 -> 1168 | M81: =Disclosures!H41 -> 1168 | N81: =(Disclosures!I41*365-Disclosures!H41*181)/184 -> 1161.8056 | O81: =(Disclosures!I41*365-Disclosures!H41*181)/184 -> 1161.8056 | P81: =Disclosures!J41 -> 1153 | Q81: =Disclosures!J41 -> 1153
C82: Half-year distribution costs | D82: =Disclosures!D21 -> 16 | E82: =Disclosures!D21 -> 16 | F82: =Disclosures!E21-Disclosures!D21 -> 16 | G82: =Disclosures!E21-Disclosures!D21 -> 16 | H82: =Disclosures!F21 -> 17 | I82: =Disclosures!F21 -> 17 | J82: =Disclosures!G21-Disclosures!F21 -> 21 | K82: =Disclosures!G21-Disclosures!F21 -> 21 | L82: =Disclosures!H21 -> 26 | M82: =Disclosures!H21 -> 26 | N82: =Disclosures!I21-Disclosures!H21 -> 33 | O82: =Disclosures!I21-Disclosures!H21 -> 33 | P82: =Disclosures!J21 -> 43 | Q82: =Disclosures!J21 -> 43
C85: H1 / FY ROLLUPS | QUARTERS REMAIN THE PRIMARY MODEL
D86: H1:23 | E86: FY:23 | F86: H1:24 | G86: FY:24 | H86: H1:25 | I86: FY:25 | J86: H1:26 | K86: FY:26 | L86: H1:27 | M86: FY:27
C87: Closing fee-paying AUM | D87: =E17 -> 151.7 | E87: =G17 -> 167.5 | F87: =I17 -> 178.2 | G87: =K17 -> 168.6 | H87: =M17 -> 193.3 | I87: =O17 -> 227.6 | J87: =Q17 -> 253.6 | K87: =S17 -> 266.4385 | L87: =U17 -> 279.92695 | M87: =W17 -> 294.09825
C88: Average AUM: opening / closing midpoint | D88: =AVERAGE(D18:E18) -> 146.1 | E88: =AVERAGE(D18:G18) -> 153.25 | F88: =AVERAGE(H18:I18) -> 174.275 | G88: =AVERAGE(H18:K18) -> 174.2125 | H88: =AVERAGE(L18:M18) -> 176.775 | I88: =AVERAGE(L18:O18) -> 194.475 | J88: =AVERAGE(P18:Q18) -> 234.65 | K88: =AVERAGE(P18:S18) -> 247.31481 | L88: =AVERAGE(T18:U18) -> 273.14109 | M88: =AVERAGE(T18:W18) -> 280.05498
C89: Net flows | D89: =SUM(D11:E11) -> 2.6 | E89: =SUM(D11:G11) -> 3 | F89: =SUM(H11:I11) -> 0.9 | G89: =SUM(H11:K11) -> -3.3 | H89: =SUM(L11:M11) -> 17.6 | I89: =SUM(L11:O11) -> 28.7 | J89: =SUM(P11:Q11) -> 7.1 | K89: =SUM(P11:S11) -> 12.2354 | L89: =SUM(T11:U11) -> 5.3953796 | M89: =SUM(T11:W11) -> 11.0639
C90: Investment performance | D90: =SUM(D12:E12) -> 5.1 | E90: =SUM(D12:G12) -> 9.7 | F90: =SUM(H12:I12) -> 11.1 | G90: =SUM(H12:K12) -> 10.9 | H90: =SUM(L12:M12) -> 2.5 | I90: =SUM(L12:O12) -> 21.4 | J90: =SUM(P12:Q12) -> 19.8 | K90: =SUM(P12:S12) -> 27.5031 | L90: =SUM(T12:U12) -> 8.0930694 | M90: =SUM(T12:W12) -> 16.595851
C91: FX: allocated when annual split disclosed | D91: =IF(COUNT(D13:E13)=2,SUM(D13:E13),"n/d") -> n/d | E91: =IF(COUNT(D13:G13)=4,SUM(D13:G13),"n/d") -> n/d | F91: =IF(COUNT(H13:I13)=2,SUM(H13:I13),"n/d") -> -0.76 | G91: =IF(COUNT(H13:K13)=4,SUM(H13:K13),"n/d") -> -3.8 | H91: =IF(COUNT(L13:M13)=2,SUM(L13:M13),"n/d") -> 4.9709677 | I91: =IF(COUNT(L13:O13)=4,SUM(L13:O13),"n/d") -> 6.7 | J91: =IF(COUNT(P13:Q13)=2,SUM(P13:Q13),"n/d") -> n/d | K91: =IF(COUNT(P13:S13)=4,SUM(P13:S13),"n/d") -> n/d | L91: =IF(COUNT(T13:U13)=2,SUM(T13:U13),"n/d") -> 0 | M91: =IF(COUNT(T13:W13)=4,SUM(T13:W13),"n/d") -> 0
C92: Acquisitions | D92: =SUM(D14:E14) -> 0 | E92: =SUM(D14:G14) -> 10.8 | F92: =SUM(H14:I14) -> 0 | G92: =SUM(H14:K14) -> 0 | H92: =SUM(L14:M14) -> 0 | I92: =SUM(L14:O14) -> 2.7 | J92: =SUM(P14:Q14) -> 0 | K92: =SUM(P14:S14) -> 0 | L92: =SUM(T14:U14) -> 0 | M92: =SUM(T14:W14) -> 0
C93: Realisations: allocated when disclosed | D93: =IF(COUNT(D15:E15)=2,SUM(D15:E15),"n/d") -> n/d | E93: =IF(COUNT(D15:G15)=4,SUM(D15:G15),"n/d") -> n/d | F93: =IF(COUNT(H15:I15)=2,SUM(H15:I15),"n/d") -> -1.05 | G93: =IF(COUNT(H15:K15)=4,SUM(H15:K15),"n/d") -> -2.1 | H93: =IF(COUNT(L15:M15)=2,SUM(L15:M15),"n/d") -> n/d | I93: =IF(COUNT(L15:O15)=4,SUM(L15:O15),"n/d") -> n/d | J93: =IF(COUNT(P15:Q15)=2,SUM(P15:Q15),"n/d") -> n/d | K93: =IF(COUNT(P15:S15)=4,SUM(P15:S15),"n/d") -> n/d | L93: =IF(COUNT(T15:U15)=2,SUM(T15:U15),"n/d") -> 0 | M93: =IF(COUNT(T15:W15)=4,SUM(T15:W15),"n/d") -> 0
C94: Other, including unseparated FX / exits | D94: =SUM(D16:E16) -> 0.7 | E94: =SUM(D16:G16) -> 0.7 | F94: =SUM(H16:I16) -> 0.51 | G94: =SUM(H16:K16) -> -0.6 | H94: =SUM(L16:M16) -> -0.37096774 | I94: =SUM(L16:O16) -> -0.5 | J94: =SUM(P16:Q16) -> -0.9 | K94: =SUM(P16:S16) -> -0.9 | L94: =SUM(T16:U16) -> 0 | M94: =SUM(T16:W16) -> 0
C95: Net management fees | D95: =SUM(D27:E27) -> 460 | E95: =SUM(D27:G27) -> 963 | F95: =SUM(H27:I27) -> 551 | G95: =SUM(H27:K27) -> 1097 | H95: =SUM(L27:M27) -> 517 | I95: =SUM(L27:O27) -> 1077 | J95: =SUM(P27:Q27) -> 627 | K95: =SUM(P27:S27) -> 1354.9429 | L95: =SUM(T27:U27) -> 764.79506 | M95: =SUM(T27:W27) -> 1568.3079
C96: Performance fees / carried interest | D96: =SUM(D28:E28) -> 32 | E96: =SUM(D28:G28) -> 180 | F96: =SUM(H28:I28) -> 170 | G96: =SUM(H28:K28) -> 310 | H96: =SUM(L28:M28) -> 67 | I96: =SUM(L28:O28) -> 281 | J96: =SUM(P28:Q28) -> 207 | K96: =SUM(P28:S28) -> 421 | L96: =SUM(T28:U28) -> 67 | M96: =SUM(T28:W28) -> 281
C97: Seed investment gains | D97: =SUM(D29:E29) -> 19 | E97: =SUM(D29:G29) -> 48 | F97: =SUM(H29:I29) -> 39 | G97: =SUM(H29:K29) -> 50 | H97: =SUM(L29:M29) -> 19 | I97: =SUM(L29:O29) -> 38 | J97: =SUM(P29:Q29) -> 18 | K97: =SUM(P29:S29) -> 37 | L97: =SUM(T29:U29) -> 19 | M97: =SUM(T29:W29) -> 38
C98: Rental / other income | D98: =SUM(D30:E30) -> 2 | E98: =SUM(D30:G30) -> 5 | F98: =SUM(H30:I30) -> 1 | G98: =SUM(H30:K30) -> 2 | H98: =SUM(L30:M30) -> 1 | I98: =SUM(L30:O30) -> 2 | J98: =SUM(P30:Q30) -> 1 | K98: =SUM(P30:S30) -> 2 | L98: =SUM(T30:U30) -> 1 | M98: =SUM(T30:W30) -> 2
C99: Core net revenue | D99: =SUM(D31:E31) -> 513 | E99: =SUM(D31:G31) -> 1196 | F99: =SUM(H31:I31) -> 761 | G99: =SUM(H31:K31) -> 1459 | H99: =SUM(L31:M31) -> 604 | I99: =SUM(L31:O31) -> 1398 | J99: =SUM(P31:Q31) -> 853 | K99: =SUM(P31:S31) -> 1814.9429 | L99: =SUM(T31:U31) -> 851.79506 | M99: =SUM(T31:W31) -> 1889.3079
C100: Total core operating costs | D100: =SUM(D42:E42) -> -370 | E100: =SUM(D42:G42) -> -834 | F100: =SUM(H42:I42) -> -487 | G100: =SUM(H42:K42) -> -960 | H100: =SUM(L42:M42) -> -449 | I100: =SUM(L42:O42) -> -970 | J100: =SUM(P42:Q42) -> -546 | K100: =SUM(P42:S42) -> -1124.4043 | L100: =SUM(T42:U42) -> -498.55941 | M100: =SUM(T42:W42) -> -1096.5538
C101: Core operating profit including seed gains | D101: =SUM(D44:E44) -> 143 | E101: =SUM(D44:G44) -> 362 | F101: =SUM(H44:I44) -> 274 | G101: =SUM(H44:K44) -> 499 | H101: =SUM(L44:M44) -> 155 | I101: =SUM(L44:O44) -> 428 | J101: =SUM(P44:Q44) -> 307 | K101: =SUM(P44:S44) -> 690.53863 | L101: =SUM(T44:U44) -> 353.23566 | M101: =SUM(T44:W44) -> 792.75411
C102: Core management-fee profit before tax | D102: =SUM(D51:E51) -> 133 | E102: =SUM(D51:G51) -> 280 | F102: =SUM(H51:I51) -> 163 | G102: =SUM(H51:K51) -> 323 | H102: =SUM(L51:M51) -> 130 | I102: =SUM(L51:O51) -> 294 | J102: =SUM(P51:Q51) -> 186 | K102: =SUM(P51:S51) -> 473.73769 | L102: =SUM(T51:U51) -> 315.0366 | M102: =SUM(T51:W51) -> 658.75411
C103: Core performance / seed profit before tax | D103: =SUM(D52:E52) -> 4 | E103: =SUM(D52:G52) -> 60 | F103: =SUM(H52:I52) -> 94 | G103: =SUM(H52:K52) -> 150 | H103: =SUM(L52:M52) -> 16 | I103: =SUM(L52:O52) -> 113 | J103: =SUM(P52:Q52) -> 111 | K103: =SUM(P52:S52) -> 196.03937 | L103: =SUM(T52:U52) -> 27.960625 | M103: =SUM(T52:W52) -> 113
C104: Core total profit before tax | D104: =SUM(D53:E53) -> 137 | E104: =SUM(D53:G53) -> 340 | F104: =SUM(H53:I53) -> 257 | G104: =SUM(H53:K53) -> 473 | H104: =SUM(L53:M53) -> 146 | I104: =SUM(L53:O53) -> 407 | J104: =SUM(P53:Q53) -> 297 | K104: =SUM(P53:S53) -> 669.77706 | L104: =SUM(T53:U53) -> 342.99722 | M104: =SUM(T53:W53) -> 771.75411
C105: Core tax expense | D105: =SUM(D54:E54) -> -29 | E105: =SUM(D54:G54) -> -69 | F105: =SUM(H54:I54) -> -53 | G105: =SUM(H54:K54) -> -92 | H105: =SUM(L54:M54) -> -33 | I105: =SUM(L54:O54) -> -86 | J105: =SUM(P54:Q54) -> -67 | K105: =SUM(P54:S54) -> -145.76862 | L105: =SUM(T54:U54) -> -72.476071 | M105: =SUM(T54:W54) -> -163.07335
C106: Core profit after tax | D106: =SUM(D55:E55) -> 108 | E106: =SUM(D55:G55) -> 271 | F106: =SUM(H55:I55) -> 204 | G106: =SUM(H55:K55) -> 381 | H106: =SUM(L55:M55) -> 113 | I106: =SUM(L55:O55) -> 321 | J106: =SUM(P55:Q55) -> 230 | K106: =SUM(P55:S55) -> 524.00844 | L106: =SUM(T55:U55) -> 270.52115 | M106: =SUM(T55:W55) -> 608.68076
C107: Diluted weighted average shares, m | D107: =(D56*90+E56*91)/181 -> 1217 | E107: =(D56*90+E56*91+F56*92+G56*92)/365 -> 1207.0554 | F107: =(H56*91+I56*91)/182 -> 1192 | G107: =(H56*91+I56*91+J56*92+K56*92)/366 -> 1189.0758 | H107: =(L56*90+M56*91)/181 -> 1168 | I107: =(L56*90+M56*91+N56*92+O56*92)/365 -> 1164.8774 | J107: =(P56*90+Q56*91)/181 -> 1153 | K107: =(P56*90+Q56*91+R56*92+S56*92)/365 -> 1158.9875 | L107: =(T56*90+U56*91)/181 -> 1164.8774 | M107: =(T56*90+U56*91+V56*92+W56*92)/365 -> 1164.8774
C108: Core diluted EPS, US cents | D108: =D106/D107*Assumptions!$D$61 -> 8.874281 | E108: =E106/E107*Assumptions!$D$61 -> 22.45133 | F108: =F106/F107*Assumptions!$D$61 -> 17.114094 | G108: =G106/G107*Assumptions!$D$61 -> 32.04169 | H108: =H106/H107*Assumptions!$D$61 -> 9.6746575 | I108: =I106/I107*Assumptions!$D$61 -> 27.556549 | J108: =J106/J107*Assumptions!$D$61 -> 19.947962 | K108: =K106/K107*Assumptions!$D$61 -> 45.212606 | ... M108: =M106/M107*Assumptions!$D$61 -> 52.252776
C109: Net management-fee margin, annual bp | D109: =D95/D88/Assumptions!$D$49*Assumptions!$D$60/0.5 -> 62.970568 | E109: =E95/E88/Assumptions!$D$49*Assumptions!$D$60/1 -> 62.838499 | F109: =F95/F88/Assumptions!$D$49*Assumptions!$D$60/0.5 -> 63.233395 | G109: =G95/G88/Assumptions!$D$49*Assumptions!$D$60/1 -> 62.969075 | H109: =H95/H88/Assumptions!$D$49*Assumptions!$D$60/0.5 -> 58.492434 | I109: =I95/I88/Assumptions!$D$49*Assumptions!$D$60/1 -> 55.379869 | J109: =J95/J88/Assumptions!$D$49*Assumptions!$D$60/0.5 -> 53.441296 | K109: =K95/K88/Assumptions!$D$49*Assumptions!$D$60/1 -> 54.786162 | L109: =L95/L88/Assumptions!$D$49*Assumptions!$D$60/0.5 -> 56 | M109: =M95/M88/Assumptions!$D$49*Assumptions!$D$60/1 -> 56

Sheet Disclosures
C2: Man Group | reported evidence
C4: Case selected | D4: =Assumptions!$E$4 -> Base
C5: USD bn AUM; USD m financials; EPS in US cents. Costs shown as positive inputs.
C7: QUARTERLY AUM | REPORTED STOCKS AND FLOWS
D8: Q1:23 | E8: Q2:23 | F8: Q3:23 | G8: Q4:23 | H8: Q1:24 | I8: Q2:24 | J8: Q3:24 | K8: Q4:24 | L8: Q1:25 | M8: Q2:25 | N8: Q3:25 | O8: Q4:25 | P8: Q1:26 | Q8: Q2:26
C9: Opening AUM | D9: 143.3 | E9: 144.7 | F9: 151.7 | G9: 161.2 | H9: 167.5 | I9: 175.7 | J9: 178.2 | K9: 174.9 | L9: 168.6 | M9: 172.6 | N9: 193.3 | O9: 213.9 | P9: 227.6 | Q9: 228.7
C10: Net flows | D10: 1.1 | E10: 1.5 | F10: 0.7 | G10: -0.3 | H10: -1.6 | I10: 2.5 | J10: -5.5 | K10: 1.3 | L10: 3.6 | M10: 14 | N10: 9.7 | O10: 1.4 | P10: -1.6 | Q10: 8.7
C11: Investment performance | D11: 0.7 | E11: 4.4 | F11: 0.1 | G11: 4.5 | H11: 9.8 | I11: 1.3 | J11: 0.4 | K11: -0.6 | L11: -1.1 | M11: 3.6 | N11: 10 | O11: 8.9 | P11: 3.1 | Q11: 16.7
C12: Reported FX and other bucket | D12: -0.4 | E12: 1.1 | F12: 8.7 | G12: 2.1 | H12: 0 | I12: -1.3 | J12: 1.8 | K12: -7 | L12: 1.5 | M12: 3.1 | N12: 0.9 | O12: 3.4 | P12: -0.4 | Q12: -0.5
C13: Closing AUM | D13: 144.7 | E13: 151.7 | F13: 161.2 | G13: 167.5 | H13: 175.7 | I13: 178.2 | J13: 174.9 | K13: 168.6 | L13: 172.6 | M13: 193.3 | N13: 213.9 | O13: 227.6 | P13: 228.7 | Q13: 253.6
C14: Acquisitions identified within other | D14: 0 | E14: 0 | F14: 10.8 | G14: 0 | H14: 0 | I14: 0 | J14: 0 | K14: 0 | L14: 0 | M14: 0 | N14: 0 | O14: 2.7 | P14: 0 | Q14: 0
C15: Source ID | D15: S01 | E15: S02 | F15: S03 | G15: S04 | H15: S05 | I15: S06 | J15: S07 | K15: S08 | L15: S09 | M15: S10 | N15: S11 | O15: S12 | P15: S13 | Q15: S14
C18: H1 / FY CORE FINANCIALS | COMPANY DISCLOSURES
D19: H1:23 | E19: FY:23 | F19: H1:24 | G19: FY:24 | H19: H1:25 | I19: FY:25 | J19: H1:26
C20: Gross management and other fees | D20: 476 | E20: 995 | F20: 568 | G20: 1135 | H20: 543 | I20: 1136 | J20: 670
C21: Distribution costs | D21: 16 | E21: 32 | F21: 17 | G21: 38 | H21: 26 | I21: 59 | J21: 43
C22: Core net management fees | D22: 460 | E22: 963 | F22: 551 | G22: 1097 | H22: 517 | I22: 1077 | J22: 627
C23: Core performance fees | D23: 32 | E23: 180 | F23: 170 | G23: 310 | H23: 67 | I23: 281 | J23: 207
C24: Core investment gains | D24: 19 | E24: 48 | F24: 39 | G24: 50 | H24: 19 | I24: 38 | J24: 18
C25: Core rental / other income | D25: 2 | E25: 5 | F25: 1 | G25: 2 | H25: 1 | I25: 2 | J25: 1
C26: Asset servicing costs | D26: 27 | E26: 58 | F26: 33 | G26: 67 | H26: 35 | I26: 73 | J26: 39
C27: Fixed compensation | D27: 118 | E27: 239 | F27: 134 | G27: 264 | H27: 141 | I27: 274 | J27: 143
C28: Management-fee compensation | D28: 215 | E28: 439 | F28: 251 | G28: 490 | H28: 239 | I28: 481 | J28: 282
C29: Performance-fee compensation | D29: 42 | E29: 156 | F29: 107 | G29: 194 | H29: 63 | I29: 194 | J29: 109
C30: Core other costs, including D&A | D30: 86 | E30: 179 | F30: 93 | G30: 199 | H30: 110 | I30: 215 | J30: 113
C31: Core other employment expenses | D31: 0 | E31: 2 | F31: 3 | G31: 10 | H31: 2 | I31: 7 | J31: 3
... C44: Reported statutory diluted EPS, US cents | D44: 6.8 | E44: 19.4 | F44: 13.8 | G44: 25.1 | H44: 4.4 | I44: 15 | J44: 17.5
C45: Published average fee margin, bp | D45: n/d | E45: 63 | F45: n/d | G45: 63 | H45: n/d | I45: 56 | J45: 52
C46: Source IDs | D46: S02 | E46: S04 | F46: S06 | G46: S08 | H46: S10 | I46: S12 | J46: S14
C49: ANNUAL AUM DETAIL | SEPARATELY DISCLOSED
D50: FY:23 | E50: FY:24 | F50: FY:25
C51: FX impact, USD bn | D51: n/d | E51: -3.8 | F51: 6.7
C52: Realisations / maturities, USD bn | D52: n/d | E52: -2.1 | F52: n/d
C53: Total net flows, USD bn | D53: 3 | E53: -3.3 | F53: 28.7
C54: Total investment performance, USD bn | D54: 9.7 | E54: 10.9 | F54: 21.4
C55: Total reported FX and other, USD bn | D55: 11.5 | E55: -6.5 | F55: 8.9
C56: Source IDs | D56: S04 | E56: S08 | F56: S12
C59: 2025 MIX | AUM STOCK VS MANAGEMENT-FEE FLOW
C60: Product category | D60: Closing AUM, bn | E60: Net fees, m | F60: Margin, bp | H60: S12 | FY2025 revenue table, page 11
C61: Absolute return | D61: 42.5 | E61: 426 | F61: 105
C62: Total return | D62: 46.6 | E62: 269 | F62: 63
C63: Multi-manager | D63: 14.5 | E63: 28 | F63: 20
C64: Systematic long-only | D64: 76.2 | E64: 136 | F64: 24
C65: Discretionary long-only | D65: 47.8 | E65: 215 | F65: 57
C66: Other service income | D66: 0 | E66: 3 | F66: n/a
C69: SOURCE REGISTER | ISSUER DISCLOSURES ACCESSED 14 SEP 2026
C71: S01 | Q1:23 | D71: 2023-04-26 | E71: EMG:LN_20230426_Q1_8K
C72: Evidence location | D72: AUM bridge, p1
C73: Issuer source | D73: https://www.man.com/shareholder-relations
C75: S02 | H1:23 | D75: 2023-08-01 | E75: EMG:LN_20230801_H1_8K
C76: Evidence location | D76: AUM p5; core reconciliation pp29–32; EPS note 7
C77: Issuer source | D77: https://www.man.com/news-centre/half-year-results-for-the-six-months-ended-30-june-2023
C79: S03 | Q3:23 | D79: 2023-10-19 | E79: EMG:LN_20231019_Q3_8K
C80: Evidence location | D80: AUM bridge, p1
C81: Issuer source | D81: https://www.man.com/shareholder-relations
C83: S04 | FY:23 | D83: 2024-02-29 | E83: EMG:LN_20240229_H2_8K
C84: Evidence location | D84: AUM p5; review pp13–16; core pp58–63; EPS note 9
C85: Issuer source | D85: https://www.man.com/news-centre/results-for-the-financial-year-ended-31-december-2023
C87: S05 | Q1:24 | D87: 2024-04-19 | E87: EMG:LN_20240419_Q1_8K
C88: Evidence location | D88: AUM bridge, p1
C89: Issuer source | D89: https://www.man.com/shareholder-relations
C91: S06 | H1:24 | D91: 2024-07-26 | E91: EMG:LN_20240726_H1_8K
C92: Evidence location | D92: AUM p5; core pp31–34; EPS note 7
C93: Issuer source | D93: https://www.man.com/news-centre/half-year-results-for-the-six-months-ended-30-june-2024
C95: S07 | Q3:24 | D95: 2024-10-17 | E95: EMG:LN_20241017_Q3_8K
C96: Evidence location | D96: AUM bridge, p1
C97: Issuer source | D97: https://www.man.com/shareholder-relations
C99: S08 | FY:24 | D99: 2025-02-27 | E99: EMG:LN_20250227_H2_8K
C100: Evidence location | D100: AUM p4; core pp62–67; compensation note 6.1; EPS note 13
C101: Issuer source | D101: https://www.man.com/news-centre/results-for-the-financial-year-ended-31-december-2024
C103: S09 | Q1:25 | D103: 2025-04-17 | E103: EMG:LN_20250417_Q1_8K
C104: Evidence location | D104: AUM bridge, p1
C105: Issuer source | D105: https://www.man.com/shareholder-relations
C107: S10 | H1:25 | D107: 2025-07-30 | E107: EMG:LN_20250730_H1_8K
C108: Evidence location | D108: AUM p4; core pp33–37; EPS note 7
C109: Issuer source | D109: https://www.man.com/news-centre/half-year-results-for-the-six-months-ended-30-june-2025
C111: S11 | Q3:25 | D111: 2025-10-17 | E111: EMG:LN_20251017_Q3_8K
C112: Evidence location | D112: AUM bridge, p1
C113: Issuer source | D113: https://www.man.com/shareholder-relations
C115: S12 | FY:25 | D115: 2026-02-26 | E115: EMG:LN_20260226_H2_8K
C116: Evidence location | D116: AUM p3; core pp50–55; compensation note 6.1; EPS note 13
C117: Issuer source | D117: https://www.man.com/news-centre/results-for-the-financial-year-ended-31-december-2025
C119: S13 | Q1:26 | D119: 2026-04-23 | E119: EMG:LN_20260423_Q1_8K
C120: Evidence location | D120: AUM bridge, pp1–2
C121: Issuer source | D121: https://www.man.com/shareholder-relations
C123: S14 | H1:26 | D123: 2026-07-28 | E123: EMG:LN_20260728_H1_8K
C124: Evidence location | D124: AUM pp4–5; core pp23–26; EPS note 9
C125: Issuer source | D125: https://www.man.com/news-centre/trading-statement-30-june-2026

Sheet Checks
C2: Man Group | model diagnostics
C4: Case selected | D4: =Assumptions!$E$4 -> Base
C5: Differences are model less disclosure. Zero is expected; EPS allows 0.10c for rounded source earnings.
C7: QUARTERLY AUM | SOURCE TIE-OUT
D8: Q1:23 | E8: Q2:23 | F8: Q3:23 | G8: Q4:23 | H8: Q1:24 | I8: Q2:24 | J8: Q3:24 | K8: Q4:24 | L8: Q1:25 | M8: Q2:25 | N8: Q3:25 | O8: Q4:25 | P8: Q1:26 | Q8: Q2:26
C9: Closing AUM less reported closing AUM | D9: =ROUND('Fee engine'!D17-Disclosures!D13,8) -> 0 | E9: =ROUND('Fee engine'!E17-Disclosures!E13,8) -> 0 | F9: =ROUND('Fee engine'!F17-Disclosures!F13,8) -> 0 | G9: =ROUND('Fee engine'!G17-Disclosures!G13,8) -> 0 | H9: =ROUND('Fee engine'!H17-Disclosures!H13,8) -> 0 | I9: =ROUND('Fee engine'!I17-Disclosures!I13,8) -> 0 | J9: =ROUND('Fee engine'!J17-Disclosures!J13,8) -> 0 | K9: =ROUND('Fee engine'!K17-Disclosures!K13,8) -> 0 | ... Q9: =ROUND('Fee engine'!Q17-Disclosures!Q13,8) -> 0
C10: Rebuilt other bucket less reported other | D10: =ROUND(SUM('Fee engine'!D13:D16)-Disclosures!D12,8) -> 0 | E10: =ROUND(SUM('Fee engine'!E13:E16)-Disclosures!E12,8) -> 0 | F10: =ROUND(SUM('Fee engine'!F13:F16)-Disclosures!F12,8) -> 0 | G10: =ROUND(SUM('Fee engine'!G13:G16)-Disclosures!G12,8) -> 0 | H10: =ROUND(SUM('Fee engine'!H13:H16)-Disclosures!H12,8) -> 0 | I10: =ROUND(SUM('Fee engine'!I13:I16)-Disclosures!I12,8) -> 0 | J10: =ROUND(SUM('Fee engine'!J13:J16)-Disclosures!J12,8) -> 0 | K10: =ROUND(SUM('Fee engine'!K13:K16)-Disclosures!K12,8) -> 0 | ... Q10: =ROUND(SUM('Fee engine'!Q13:Q16)-Disclosures!Q12,8) -> 0
C13: H1 / FY FINANCIALS | INDEPENDENT DISCLOSURE CONTROLS
D14: H1:23 | E14: FY:23 | F14: H1:24 | G14: FY:24 | H14: H1:25 | I14: FY:25 | J14: H1:26
C15: Net management fees | D15: =ROUND('Fee engine'!D95-Disclosures!D22,8) -> 0 | E15: =ROUND('Fee engine'!E95-Disclosures!E22,8) -> 0 | F15: =ROUND('Fee engine'!F95-Disclosures!F22,8) -> 0 | G15: =ROUND('Fee engine'!G95-Disclosures!G22,8) -> 0 | H15: =ROUND('Fee engine'!H95-Disclosures!H22,8) -> 0 | I15: =ROUND('Fee engine'!I95-Disclosures!I22,8) -> 0 | J15: =ROUND('Fee engine'!J95-Disclosures!J22,8) -> 0
C16: Performance fees | D16: =ROUND('Fee engine'!D96-Disclosures!D23,8) -> 0 | E16: =ROUND('Fee engine'!E96-Disclosures!E23,8) -> 0 | F16: =ROUND('Fee engine'!F96-Disclosures!F23,8) -> 0 | G16: =ROUND('Fee engine'!G96-Disclosures!G23,8) -> 0 | H16: =ROUND('Fee engine'!H96-Disclosures!H23,8) -> 0 | I16: =ROUND('Fee engine'!I96-Disclosures!I23,8) -> 0 | J16: =ROUND('Fee engine'!J96-Disclosures!J23,8) -> 0
C17: Seed gains | D17: =ROUND('Fee engine'!D97-Disclosures!D24,8) -> 0 | E17: =ROUND('Fee engine'!E97-Disclosures!E24,8) -> 0 | F17: =ROUND('Fee engine'!F97-Disclosures!F24,8) -> 0 | G17: =ROUND('Fee engine'!G97-Disclosures!G24,8) -> 0 | H17: =ROUND('Fee engine'!H97-Disclosures!H24,8) -> 0 | I17: =ROUND('Fee engine'!I97-Disclosures!I24,8) -> 0 | J17: =ROUND('Fee engine'!J97-Disclosures!J24,8) -> 0
C18: Rental / other income | D18: =ROUND('Fee engine'!D98-Disclosures!D25,8) -> 0 | E18: =ROUND('Fee engine'!E98-Disclosures!E25,8) -> 0 | F18: =ROUND('Fee engine'!F98-Disclosures!F25,8) -> 0 | G18: =ROUND('Fee engine'!G98-Disclosures!G25,8) -> 0 | H18: =ROUND('Fee engine'!H98-Disclosures!H25,8) -> 0 | I18: =ROUND('Fee engine'!I98-Disclosures!I25,8) -> 0 | J18: =ROUND('Fee engine'!J98-Disclosures!J25,8) -> 0
C19: Management-fee PBT | D19: =ROUND('Fee engine'!D102-Disclosures!D36,8) -> 0 | E19: =ROUND('Fee engine'!E102-Disclosures!E36,8) -> 0 | F19: =ROUND('Fee engine'!F102-Disclosures!F36,8) -> 0 | G19: =ROUND('Fee engine'!G102-Disclosures!G36,8) -> 0 | H19: =ROUND('Fee engine'!H102-Disclosures!H36,8) -> 0 | I19: =ROUND('Fee engine'!I102-Disclosures!I36,8) -> 0 | J19: =ROUND('Fee engine'!J102-Disclosures!J36,8) -> 0
C20: Performance / seed PBT | D20: =ROUND('Fee engine'!D103-Disclosures!D37,8) -> 0 | E20: =ROUND('Fee engine'!E103-Disclosures!E37,8) -> 0 | F20: =ROUND('Fee engine'!F103-Disclosures!F37,8) -> 0 | G20: =ROUND('Fee engine'!G103-Disclosures!G37,8) -> 0 | H20: =ROUND('Fee engine'!H103-Disclosures!H37,8) -> 0 | I20: =ROUND('Fee engine'!I103-Disclosures!I37,8) -> 0 | J20: =ROUND('Fee engine'!J103-Disclosures!J37,8) -> 0
C21: Total core PBT | D21: =ROUND('Fee engine'!D104-Disclosures!D38,8) -> 0 | E21: =ROUND('Fee engine'!E104-Disclosures!E38,8) -> 0 | F21: =ROUND('Fee engine'!F104-Disclosures!F38,8) -> 0 | G21: =ROUND('Fee engine'!G104-Disclosures!G38,8) -> 0 | H21: =ROUND('Fee engine'!H104-Disclosures!H38,8) -> 0 | I21: =ROUND('Fee engine'!I104-Disclosures!I38,8) -> 0 | J21: =ROUND('Fee engine'!J104-Disclosures!J38,8) -> 0
C22: Core tax expense | D22: =ROUND(-'Fee engine'!D105-Disclosures!D39,8) -> 0 | E22: =ROUND(-'Fee engine'!E105-Disclosures!E39,8) -> 0 | F22: =ROUND(-'Fee engine'!F105-Disclosures!F39,8) -> 0 | G22: =ROUND(-'Fee engine'!G105-Disclosures!G39,8) -> 0 | H22: =ROUND(-'Fee engine'!H105-Disclosures!H39,8) -> 0 | I22: =ROUND(-'Fee engine'!I105-Disclosures!I39,8) -> 0 | J22: =ROUND(-'Fee engine'!J105-Disclosures!J39,8) -> 0
C23: Core profit after tax | D23: =ROUND('Fee engine'!D106-Disclosures!D40,8) -> 0 | E23: =ROUND('Fee engine'!E106-Disclosures!E40,8) -> 0 | F23: =ROUND('Fee engine'!F106-Disclosures!F40,8) -> 0 | G23: =ROUND('Fee engine'!G106-Disclosures!G40,8) -> 0 | H23: =ROUND('Fee engine'!H106-Disclosures!H40,8) -> 0 | I23: =ROUND('Fee engine'!I106-Disclosures!I40,8) -> 0 | J23: =ROUND('Fee engine'!J106-Disclosures!J40,8) -> 0
C24: Weighted diluted shares | D24: =ROUND('Fee engine'!D107-Disclosures!D41,8) -> 0 | E24: =ROUND('Fee engine'!E107-Disclosures!E41,8) -> 0 | F24: =ROUND('Fee engine'!F107-Disclosures!F41,8) -> 0 | G24: =ROUND('Fee engine'!G107-Disclosures!G41,8) -> 0 | H24: =ROUND('Fee engine'!H107-Disclosures!H41,8) -> 0 | I24: =ROUND('Fee engine'!I107-Disclosures!I41,8) -> 0 | J24: =ROUND('Fee engine'!J107-Disclosures!J41,8) -> 0
C25: Diluted EPS, US cents | D25: =ROUND('Fee engine'!D108-Disclosures!D42,8) -> -0.02571898 | E25: =ROUND('Fee engine'!E108-Disclosures!E42,8) -> 0.05132995 | F25: =ROUND('Fee engine'!F108-Disclosures!F42,8) -> 0.01409396 | G25: =ROUND('Fee engine'!G108-Disclosures!G42,8) -> -0.05830967 | H25: =ROUND('Fee engine'!H108-Disclosures!H42,8) -> -0.02534247 | I25: =ROUND('Fee engine'!I108-Disclosures!I42,8) -> -0.04345123 | J25: =ROUND('Fee engine'!J108-Disclosures!J42,8) -> 0.04796184
C27: Total compensation | D27: =ROUND(-(SUM('Fee engine'!D38:E38))-(Disclosures!D28+Disclosures!D29),8) -> 0 | E27: =ROUND(-(SUM('Fee engine'!D38:G38))-(Disclosures!E28+Disclosures!E29),8) -> 0 | F27: =ROUND(-(SUM('Fee engine'!H38:I38))-(Disclosures!F28+Disclosures!F29),8) -> 0 | G27: =ROUND(-(SUM('Fee engine'!H38:K38))-(Disclosures!G28+Disclosures!G29),8) -> 0 | H27: =ROUND(-(SUM('Fee engine'!L38:M38))-(Disclosures!H28+Disclosures!H29),8) -> 0 | I27: =ROUND(-(SUM('Fee engine'!L38:O38))-(Disclosures!I28+Disclosures!I29),8) -> 0 | J27: =ROUND(-(SUM('Fee engine'!P38:Q38))-(Disclosures!J28+Disclosures!J29),8) -> 0
C28: Fixed compensation | D28: =ROUND(-(SUM('Fee engine'!D34:E34))-(Disclosures!D27),8) -> 0 | E28: =ROUND(-(SUM('Fee engine'!D34:G34))-(Disclosures!E27),8) -> 0 | F28: =ROUND(-(SUM('Fee engine'!H34:I34))-(Disclosures!F27),8) -> 0 | G28: =ROUND(-(SUM('Fee engine'!H34:K34))-(Disclosures!G27),8) -> 0 | H28: =ROUND(-(SUM('Fee engine'!L34:M34))-(Disclosures!H27),8) -> 0 | I28: =ROUND(-(SUM('Fee engine'!L34:O34))-(Disclosures!I27),8) -> 0 | J28: =ROUND(-(SUM('Fee engine'!P34:Q34))-(Disclosures!J27),8) -> 0
C29: Management compensation | D29: =ROUND(-(SUM('Fee engine'!D34:E34)+SUM('Fee engine'!D35:E35))-(Disclosures!D28),8) -> 0 | E29: =ROUND(-(SUM('Fee engine'!D34:G34)+SUM('Fee engine'!D35:G35))-(Disclosures!E28),8) -> 0 | F29: =ROUND(-(SUM('Fee engine'!H34:I34)+SUM('Fee engine'!H35:I35))-(Disclosures!F28),8) -> 0 | G29: =ROUND(-(SUM('Fee engine'!H34:K34)+SUM('Fee engine'!H35:K35))-(Disclosures!G28),8) -> 0 | H29: =ROUND(-(SUM('Fee engine'!L34:M34)+SUM('Fee engine'!L35:M35))-(Disclosures!H28),8) -> 0 | I29: =ROUND(-(SUM('Fee engine'!L34:O34)+SUM('Fee engine'!L35:O35))-(Disclosures!I28),8) -> 0 | J29: =ROUND(-(SUM('Fee engine'!P34:Q34)+SUM('Fee engine'!P35:Q35))-(Disclosures!J28),8) -> 0
C30: Performance / seed compensation | D30: =ROUND(-(SUM('Fee engine'!D36:E36)+SUM('Fee engine'!D37:E37))-(Disclosures!D29),8) -> 0 | E30: =ROUND(-(SUM('Fee engine'!D36:G36)+SUM('Fee engine'!D37:G37))-(Disclosures!E29),8) -> 0 | F30: =ROUND(-(SUM('Fee engine'!H36:I36)+SUM('Fee engine'!H37:I37))-(Disclosures!F29),8) -> 0 | G30: =ROUND(-(SUM('Fee engine'!H36:K36)+SUM('Fee engine'!H37:K37))-(Disclosures!G29),8) -> 0 | H30: =ROUND(-(SUM('Fee engine'!L36:M36)+SUM('Fee engine'!L37:M37))-(Disclosures!H29),8) -> 0 | I30: =ROUND(-(SUM('Fee engine'!L36:O36)+SUM('Fee engine'!L37:O37))-(Disclosures!I29),8) -> 0 | J30: =ROUND(-(SUM('Fee engine'!P36:Q36)+SUM('Fee engine'!P37:Q37))-(Disclosures!J29),8) -> 0
C31: Asset servicing | D31: =ROUND(-(SUM('Fee engine'!D39:E39))-(Disclosures!D26),8) -> 0 | E31: =ROUND(-(SUM('Fee engine'!D39:G39))-(Disclosures!E26),8) -> 0 | F31: =ROUND(-(SUM('Fee engine'!H39:I39))-(Disclosures!F26),8) -> 0 | G31: =ROUND(-(SUM('Fee engine'!H39:K39))-(Disclosures!G26),8) -> 0 | H31: =ROUND(-(SUM('Fee engine'!L39:M39))-(Disclosures!H26),8) -> 0 | I31: =ROUND(-(SUM('Fee engine'!L39:O39))-(Disclosures!I26),8) -> 0 | J31: =ROUND(-(SUM('Fee engine'!P39:Q39))-(Disclosures!J26),8) -> 0
C32: Other costs incl D&A | D32: =ROUND(-(SUM('Fee engine'!D40:E40))-(Disclosures!D30),8) -> 0 | E32: =ROUND(-(SUM('Fee engine'!D40:G40))-(Disclosures!E30),8) -> 0 | F32: =ROUND(-(SUM('Fee engine'!H40:I40))-(Disclosures!F30),8) -> 0 | G32: =ROUND(-(SUM('Fee engine'!H40:K40))-(Disclosures!G30),8) -> 0 | H32: =ROUND(-(SUM('Fee engine'!L40:M40))-(Disclosures!H30),8) -> 0 | I32: =ROUND(-(SUM('Fee engine'!L40:O40))-(Disclosures!I30),8) -> 0 | J32: =ROUND(-(SUM('Fee engine'!P40:Q40))-(Disclosures!J30),8) -> 0
C33: Other employment | D33: =ROUND(-(SUM('Fee engine'!D41:E41))-(Disclosures!D31),8) -> 0 | E33: =ROUND(-(SUM('Fee engine'!D41:G41))-(Disclosures!E31),8) -> 0 | F33: =ROUND(-(SUM('Fee engine'!H41:I41))-(Disclosures!F31),8) -> 0 | G33: =ROUND(-(SUM('Fee engine'!H41:K41))-(Disclosures!G31),8) -> 0 | H33: =ROUND(-(SUM('Fee engine'!L41:M41))-(Disclosures!H31),8) -> 0 | I33: =ROUND(-(SUM('Fee engine'!L41:O41))-(Disclosures!I31),8) -> 0 | J33: =ROUND(-(SUM('Fee engine'!P41:Q41))-(Disclosures!J31),8) -> 0
C36: ANNUAL AUM | SEPARATE CUMULATIVE DISCLOSURES
D37: FY:23 | E37: FY:24 | F37: FY:25
C38: Annual net flows | D38: =ROUND('Fee engine'!E89-Disclosures!D53,8) -> 0 | E38: =ROUND('Fee engine'!G89-Disclosures!E53,8) -> 0 | F38: =ROUND('Fee engine'!I89-Disclosures!F53,8) -> 0
C39: Annual investment performance | D39: =ROUND('Fee engine'!E90-Disclosures!D54,8) -> 0 | E39: =ROUND('Fee engine'!G90-Disclosures!E54,8) -> 0 | F39: =ROUND('Fee engine'!I90-Disclosures!F54,8) -> 0
C40: Annual FX and other bucket | D40: =ROUND(SUM('Fee engine'!E91:E94)-Disclosures!D55,8) -> 0 | E40: =ROUND(SUM('Fee engine'!G91:G94)-Disclosures!E55,8) -> 0 | F40: =ROUND(SUM('Fee engine'!I91:I94)-Disclosures!F55,8) -> 0
C41: Annual FX allocation | D41: n/d | E41: =ROUND('Fee engine'!G91-Disclosures!E51,8) -> 0 | F41: =ROUND('Fee engine'!I91-Disclosures!F51,8) -> 0
C42: Annual realisations allocation | D42: n/d | E42: =ROUND('Fee engine'!G93-Disclosures!E52,8) -> 0 | F42: n/d
C45: FORECAST MECHANICS | ACTIVE CASE
R46: Q3:26 | S46: Q4:26 | T46: Q1:27 | U46: Q2:27 | V46: Q3:27 | W46: Q4:27
C47: Net flows assumption | R47: =ROUND('Fee engine'!R11-'Fee engine'!R10*Assumptions!R11,8) -> 0 | S47: =ROUND('Fee engine'!S11-'Fee engine'!S10*Assumptions!S11,8) -> 0 | T47: =ROUND('Fee engine'!T11-'Fee engine'!T10*Assumptions!T11,8) -> 0 | U47: =ROUND('Fee engine'!U11-'Fee engine'!U10*Assumptions!U11,8) -> 0 | V47: =ROUND('Fee engine'!V11-'Fee engine'!V10*Assumptions!V11,8) -> 0 | W47: =ROUND('Fee engine'!W11-'Fee engine'!W10*Assumptions!W11,8) -> 0
C48: Investment-return assumption | R48: =ROUND('Fee engine'!R12-'Fee engine'!R10*Assumptions!R18,8) -> 0 | S48: =ROUND('Fee engine'!S12-'Fee engine'!S10*Assumptions!S18,8) -> 0 | T48: =ROUND('Fee engine'!T12-'Fee engine'!T10*Assumptions!T18,8) -> 0 | U48: =ROUND('Fee engine'!U12-'Fee engine'!U10*Assumptions!U18,8) -> 0 | V48: =ROUND('Fee engine'!V12-'Fee engine'!V10*Assumptions!V18,8) -> 0 | W48: =ROUND('Fee engine'!W12-'Fee engine'!W10*Assumptions!W18,8) -> 0
C49: Fee-margin assumption | R49: =ROUND('Fee engine'!R26-Assumptions!R25,8) -> 0 | S49: =ROUND('Fee engine'!S26-Assumptions!S25,8) -> 0 | T49: =ROUND('Fee engine'!T26-Assumptions!T25,8) -> 0 | U49: =ROUND('Fee engine'!U26-Assumptions!U25,8) -> 0 | V49: =ROUND('Fee engine'!V26-Assumptions!V25,8) -> 0 | W49: =ROUND('Fee engine'!W26-Assumptions!W25,8) -> 0
C50: Performance-fee assumption | R50: =ROUND('Fee engine'!R28-Assumptions!R32,8) -> 0 | S50: =ROUND('Fee engine'!S28-Assumptions!S32,8) -> 0 | T50: =ROUND('Fee engine'!T28-Assumptions!T32,8) -> 0 | U50: =ROUND('Fee engine'!U28-Assumptions!U32,8) -> 0 | V50: =ROUND('Fee engine'!V28-Assumptions!V32,8) -> 0 | W50: =ROUND('Fee engine'!W28-Assumptions!W32,8) -> 0
C51: Fee-linked variable compensation | R51: =ROUND('Fee engine'!R36+'Fee engine'!R28*Assumptions!$D$52,8) -> 0 | S51: =ROUND('Fee engine'!S36+'Fee engine'!S28*Assumptions!$D$52,8) -> 0 | T51: =ROUND('Fee engine'!T36+'Fee engine'!T28*Assumptions!$D$52,8) -> 0 | U51: =ROUND('Fee engine'!U36+'Fee engine'!U28*Assumptions!$D$52,8) -> 0 | V51: =ROUND('Fee engine'!V36+'Fee engine'!V28*Assumptions!$D$52,8) -> 0 | W51: =ROUND('Fee engine'!W36+'Fee engine'!W28*Assumptions!$D$52,8) -> 0
C52: Zero non-organic AUM changes | R52: =ROUND(SUM('Fee engine'!R13:R16),8) -> 0 | S52: =ROUND(SUM('Fee engine'!S13:S16),8) -> 0 | T52: =ROUND(SUM('Fee engine'!T13:T16),8) -> 0 | U52: =ROUND(SUM('Fee engine'!U13:U16),8) -> 0 | V52: =ROUND(SUM('Fee engine'!V13:V16),8) -> 0 | W52: =ROUND(SUM('Fee engine'!W13:W16),8) -> 0
C53: Fixed compensation run-rate | R53: =ROUND('Fee engine'!R34+Assumptions!$D$54,8) -> 0 | S53: =ROUND('Fee engine'!S34+Assumptions!$D$54,8) -> 0 | T53: =ROUND('Fee engine'!T34+Assumptions!$D$54,8) -> 0 | U53: =ROUND('Fee engine'!U34+Assumptions!$D$54,8) -> 0 | V53: =ROUND('Fee engine'!V34+Assumptions!$D$54,8) -> 0 | W53: =ROUND('Fee engine'!W34+Assumptions!$D$54,8) -> 0
C54: Diluted share count | R54: =ROUND('Fee engine'!R56-Assumptions!$D$57,8) -> 0 | S54: =ROUND('Fee engine'!S56-Assumptions!$D$57,8) -> 0 | T54: =ROUND('Fee engine'!T56-Assumptions!$D$57,8) -> 0 | U54: =ROUND('Fee engine'!U56-Assumptions!$D$57,8) -> 0 | V54: =ROUND('Fee engine'!V56-Assumptions!$D$57,8) -> 0 | W54: =ROUND('Fee engine'!W56-Assumptions!$D$57,8) -> 0
C55: Effective tax rate | R55: =ROUND('Fee engine'!R60-Assumptions!$D$56,8) -> 0 | S55: =ROUND('Fee engine'!S60-Assumptions!$D$56,8) -> 0 | T55: =ROUND('Fee engine'!T60-Assumptions!$D$56,8) -> 0 | U55: =ROUND('Fee engine'!U60-Assumptions!$D$56,8) -> 0 | V55: =ROUND('Fee engine'!V60-Assumptions!$D$56,8) -> 0 | W55: =ROUND('Fee engine'!W60-Assumptions!$D$56,8) -> 0
C58: Quarterly AUM other split is an allocation check, not independent evidence of FX timing.
C59: Forecast rows test formula consistency. Scenario perturbation tests are described in Readme.

Sheet Readme
C2: Man Group | definitions and judgement
C4: Case selected | D4: =Assumptions!$E$4 -> Base
C7: Scope | D7: Twenty quarters, Q1 2023–Q4 2027. Fiscal year ends 31 December. Evidence cutoff 14 September 2026; latest actuals are H1 2026. No forecast replaces an already reported period.
C8: A / E labels | D8: AUM A / P&L E means the AUM quarter is disclosed but individual-quarter financial results are model estimates. H1 and FY earnings remain sourced actual controls. Forecast begins Q3 2026.
C9: Economic basis | D9: Core (company-adjusted) earnings remove non-core acquisition, restructuring and other adjustments, and eliminate consolidation gross-ups. Statutory profit and EPS are retained as historical memo inputs, not mixed into the forecast.
C10: AUM perimeter | D10: Use disclosed fee-paying AUM, excluding uncalled non-fee-paying commitments ($4.9bn at June 2026). Opening and closing AUM are stocks. Net flows and all earnings/costs are period flows.
C11: Average AUM | D11: A simple opening/closing midpoint assumes activity is spread through each quarter. It does not reproduce daily AUM or fund-level fee accrual. Historical fees are allocated by midpoint weights and reconcile to reported H1 and FY.
C12: Management fees | D12: Model net management fees after distribution costs. Forecast applies 56bp, the reported 2025 average, to midpoint AUM with a quarter-year factor. Immaterial service income is absorbed in this blended rate. Historical gross fees and distribution costs are shown separately as memo lines.
C13: Fee margin limitation | D13: The historical implied margin uses midpoint AUM and differs from the published margin. Base deliberately returns to the 2025 average 56bp despite H1 2026 average 52bp and 2025 exit run-rate 52bp. This is the exercise assumption; Downside tests continued 52bp.
C14: Performance-fee timing | D14: Default allocation is Q1 10% / Q2 90% of H1, and Q3 10% / Q4 90% of FY less H1. These are explicit estimates, not disclosed quarter results. Forecast copies the corresponding allocated 2025 quarter. Changing allocation alters quarters but leaves historical H1/FY intact.
C15: Recognition and carry | D15: Fees depend on fund high-water marks, benchmarks, hurdles and crystallisation. The assumed AUM investment return is therefore not multiplied by an incentive rate to generate fees. Earned carry sits within performance fees where applicable. Acquired carry receivables are stocks and are not added to revenue.
C16: Pass-through fees | D16: H1 2026 statutory performance/pass-through fees contain a $19m gross-up, with $18m of associated compensation. Core metrics remove it; the model follows the reported core basis. No unsupported standalone carry or incentive-fee series is created.
C17: Fixed costs | D17: All fixed compensation belongs to the recurring management-fee business. Forecast fixed compensation is $274m / 4 and other fixed costs including D&A $215m / 4. No inflation or incremental cost savings are assumed. Other employment expense stays $7m / 4.
C18: Variable compensation | D18: Management participation is ($481m − $274m) / $1,077m. Performance/seed participation is $194m / ($281m + $38m). The latter attribution links fee costs to fees and seed costs to seed returns while preserving the company-reported total.
... C28: Verification | D28: Recalculated every case, confirmed historical invariance, tested a later-quarter driver and missing selected/unselected inputs, and inspected each sheet. Reopened the exported workbook to verify formulas, comments and outputs. Native Excel verification is recorded in the accompanying model record.
